Workbook

Sheet Transaction Log
A1: KFC HEDGE FUND // TRANSACTION LEDGER
A2: Cash flows in and out. Fund Balance auto-updates every row.
A3: Blue = input | White = formula | Green = cross-sheet
A4: # | B4: Date | C4: Player Name | D4: Type | E4: Deposit (+) | F4: Withdrawal (−) | G4: Net Flow | H4: Fund Balance After | I4: Note / Reference | J4: Verified?
A5: =IFERROR(ROW()-4,"") -> 1 | B5: 46082 | C5: Kimmo | D5: Deposit | E5: 2000000000 | G5: =IF(AND(E5="",F5=""),"",IFERROR(E5,0)-IFERROR(F5,0)) -> 2000000000 | H5: =IF(AND(E5="",F5=""),"",G5) -> 2000000000 | I5: Fund manager initial funding | J5: Yes
A6: =IFERROR(ROW()-4,"") -> 2 | B6: 46093 | C6: Andre | D6: Deposit | E6: 50000000 | G6: =IF(AND(E6="",F6=""),"",IFERROR(E6,0)-IFERROR(F6,0)) -> 50000000 | H6: =IF(AND(E6="",F6=""),"",H5+G6) -> 2050000000 | I6: First player deposit | J6: Yes
A7: =IFERROR(ROW()-4,"") -> 3 | G7: =IF(AND(E7="",F7=""),"",IFERROR(E7,0)-IFERROR(F7,0)) | H7: =IF(AND(E7="",F7=""),"",H6+G7)
A8: =IFERROR(ROW()-4,"") -> 4 | G8: =IF(AND(E8="",F8=""),"",IFERROR(E8,0)-IFERROR(F8,0)) | H8: =IF(AND(E8="",F8=""),"",H7+G8)
A9: =IFERROR(ROW()-4,"") -> 5 | G9: =IF(AND(E9="",F9=""),"",IFERROR(E9,0)-IFERROR(F9,0)) | H9: =IF(AND(E9="",F9=""),"",H8+G9)
A10: =IFERROR(ROW()-4,"") -> 6 | G10: =IF(AND(E10="",F10=""),"",IFERROR(E10,0)-IFERROR(F10,0)) | H10: =IF(AND(E10="",F10=""),"",H9+G10)
A11: =IFERROR(ROW()-4,"") -> 7 | G11: =IF(AND(E11="",F11=""),"",IFERROR(E11,0)-IFERROR(F11,0)) | H11: =IF(AND(E11="",F11=""),"",H10+G11)
A12: =IFERROR(ROW()-4,"") -> 8 | G12: =IF(AND(E12="",F12=""),"",IFERROR(E12,0)-IFERROR(F12,0)) | H12: =IF(AND(E12="",F12=""),"",H11+G12)
A13: =IFERROR(ROW()-4,"") -> 9 | G13: =IF(AND(E13="",F13=""),"",IFERROR(E13,0)-IFERROR(F13,0)) | H13: =IF(AND(E13="",F13=""),"",H12+G13)
A14: =IFERROR(ROW()-4,"") -> 10 | G14: =IF(AND(E14="",F14=""),"",IFERROR(E14,0)-IFERROR(F14,0)) | H14: =IF(AND(E14="",F14=""),"",H13+G14)
A15: =IFERROR(ROW()-4,"") -> 11 | G15: =IF(AND(E15="",F15=""),"",IFERROR(E15,0)-IFERROR(F15,0)) | H15: =IF(AND(E15="",F15=""),"",H14+G15)
A16: =IFERROR(ROW()-4,"") -> 12 | G16: =IF(AND(E16="",F16=""),"",IFERROR(E16,0)-IFERROR(F16,0)) | H16: =IF(AND(E16="",F16=""),"",H15+G16)
A17: =IFERROR(ROW()-4,"") -> 13 | G17: =IF(AND(E17="",F17=""),"",IFERROR(E17,0)-IFERROR(F17,0)) | H17: =IF(AND(E17="",F17=""),"",H16+G17)
A18: =IFERROR(ROW()-4,"") -> 14 | G18: =IF(AND(E18="",F18=""),"",IFERROR(E18,0)-IFERROR(F18,0)) | H18: =IF(AND(E18="",F18=""),"",H17+G18)
... A106: =IFERROR(ROW()-4,"") -> 102 | G106: =IF(AND(E106="",F106=""),"",IFERROR(E106,0)-IFERROR(F106,0)) | H106: =IF(AND(E106="",F106=""),"",H105+G106)

Sheet Positions
A1: POSITIONS // TRADE TRACKER
A2: Open=live P&L | Closed=locked P&L | Blue=input | White=formula | Green=cross-sheet
A3: Col O=Exit/Cur Price | Col V=Stop Loss | Col W=Take Profit | Col AF=SL/TP Status | Col AH=Liquidation Price
A5: # | B5: Status | C5: Asset Class | D5: Ticker/Name | E5: Long/Short | F5: Entry Date | G5: Entry Price | H5: Qty | I5: Leverage (x) | J5: Margin % (1/Lev) | K5: Notional Exp ($) | L5: Margin Req ($) | M5: Warning Threshold % | N5: Margin Status | O5: Exit/Cur Price | P5: Mkt/Exit Val ($) | Q5: P&L ($) | R5: P&L (%) | S5: % of Fund | T5: Exit Date | U5: Hold (days) | V5: Stop Loss | W5: Take Profit | X5: SL Distance ($) | Y5: SL Distance (%) | Z5: TP Distance ($) | AA5: TP Distance (%) | AB5: Notes | AC5: Max Loss vs SL | AD5: Locked Exit Price | AE5: Drawdown from Entry % | AF5: SL/TP Triggered? | AG5: Auto Exit Price | AH5: Liquidation Price
A6: =IFERROR(ROW()-5,"") -> 1 | B6: Closed | C6: Stock | D6: NVDA | E6: Long | F6: 46091 | G6: 307.98 | H6: 2500000 | I6: 20 | J6: =IFERROR(1/I6,"") -> 0.05 | K6: =IFERROR(G6*H6*I6,"") -> 15399000000 | L6: =IFERROR(G6*H6,"") -> 769950000 | M6: 0.5 | N6: =IFERROR(IF(B6<>"Open","—",IF((G6*H6+Q6)<=0,"LIQUIDATION",IF((G6*H6+Q6)/(G6*H6)<=M6,"WARNING","OK"))),"—") -> — | O6: 305.56 | P6: =IFERROR((IF(AND(B6="Closed",AD6<>""),AD6,O6))*H6,"") -> 763900000 | Q6: =IFERROR(IF(E6="Long",(IF(AND(B6="Closed",AD6<>""),AD6,O6)-G6)*H6*I6,(G6-IF(AND(B6="Closed",AD6<>""),AD6,O6))*H6*I6),"") -> -1.21e+08 | R6: =IFERROR(Q6/(G6*H6),"") -> -0.15715306 | S6: =IFERROR(L6/(IFERROR(LOOKUP(2,1/('Transaction Log'!H5:H106<>""),'Transaction Log'!H5:H106),0)),"") -> 0.37558537 | T6: 46094 | U6: =IFERROR(IF(B6="Closed",T6-F6,TODAY()-F6),"") -> 3 | V6: 305.56 | W6: 312.32 | X6: =IFERROR(IF(OR(V6="",I6=""),"—",IF(E6="Long",(G6-V6)*H6*I6,(V6-G6)*H6*I6)),"—") -> 1.21e+08 | Y6: =IFERROR(IF(OR(V6="",G6=""),"—",IF(E6="Long",(G6-V6)/G6,(V6-G6)/G6)),"—") -> 0.0078576531 | Z6: =IFERROR(IF(OR(W6="",I6=""),"—",IF(E6="Long",(W6-G6)*H6*I6,(G6-W6)*H6*I6)),"—") -> 2.17e+08 | AA6: =IFERROR(IF(OR(W6="",G6=""),"—",IF(E6="Long",(W6-G6)/G6,(G6-W6)/G6)),"—") -> 0.014091824 | AC6: =IFERROR(IF(E6="Long",(G6-V6)*H6*I6,(V6-G6)*H6*I6),"") -> 1.21e+08 | AD6: =IFERROR(IF(OR(AF6="STOP LOSS HIT",AF6="TAKE PROFIT HIT"),AG6,""),"") -> 305.56 | AE6: =IFERROR(IF(E6="Long",(IF(AND(B6="Closed",AD6<>""),AD6,O6)-G6)/G6,(G6-IF(AND(B6="Closed",AD6<>""),AD6,O6))/G6),"") -> -0.0078576531 | AF6: =IFERROR(IF(OR(V6="",W6=""),"No SL/TP",IF(E6="Long",IF(O6<=V6,"STOP LOSS HIT",IF(O6>=W6,"TAKE PROFIT HIT",IF(B6="Closed","CLOSED","Active"))),IF(O6>=V6,"STOP LOSS HIT",IF(O6<=W6,"TAKE PROFIT HIT",IF(B6="Closed","CLOSED","Active"))))),"—") -> STOP LOSS HIT | AG6: =IFERROR(IF(E6="Long",IF(O6<=V6,V6,IF(O6>=W6,W6,"")),IF(O6>=V6,V6,IF(O6<=W6,W6,""))),"") -> 305.56 | AH6: =IFERROR(IF(B6<>"Open","—",IF(E6="Long",G6*(1-1/I6),G6*(1+1/I6))),"—") -> —
A7: =IFERROR(ROW()-5,"") -> 2 | B7: Closed | C7: Stock | D7: META | E7: Long | F7: 46092 | G7: 278.53 | H7: 575000 | I7: 20 | J7: =IFERROR(1/I7,"") -> 0.05 | K7: =IFERROR(G7*H7*I7,"") -> 3.203095e+09 | L7: =IFERROR(G7*H7,"") -> 1.6015475e+08 | M7: 0.5 | N7: =IFERROR(IF(B7<>"Open","—",IF((G7*H7+Q7)<=0,"LIQUIDATION",IF((G7*H7+Q7)/(G7*H7)<=M7,"WARNING","OK"))),"—") -> — | O7: 273.5 | P7: =IFERROR((IF(AND(B7="Closed",AD7<>""),AD7,O7))*H7,"") -> 157262500 | Q7: =IFERROR(IF(E7="Long",(IF(AND(B7="Closed",AD7<>""),AD7,O7)-G7)*H7*I7,(G7-IF(AND(B7="Closed",AD7<>""),AD7,O7))*H7*I7),"") -> -57845000 | R7: =IFERROR(Q7/(G7*H7),"") -> -0.36118192 | S7: =IFERROR(L7/(IFERROR(LOOKUP(2,1/('Transaction Log'!H5:H106<>""),'Transaction Log'!H5:H106),0)),"") -> 0.078124268 | T7: 46092 | U7: =IFERROR(IF(B7="Closed",T7-F7,TODAY()-F7),"") -> 0 | V7: 273.5 | W7: 294.56 | X7: =IFERROR(IF(OR(V7="",I7=""),"—",IF(E7="Long",(G7-V7)*H7*I7,(V7-G7)*H7*I7)),"—") -> 57845000 | Y7: =IFERROR(IF(OR(V7="",G7=""),"—",IF(E7="Long",(G7-V7)/G7,(V7-G7)/G7)),"—") -> 0.018059096 | Z7: =IFERROR(IF(OR(W7="",I7=""),"—",IF(E7="Long",(W7-G7)*H7*I7,(G7-W7)*H7*I7)),"—") -> 1.84345e+08 | AA7: =IFERROR(IF(OR(W7="",G7=""),"—",IF(E7="Long",(W7-G7)/G7,(G7-W7)/G7)),"—") -> 0.057552149 | AC7: =IFERROR(IF(E7="Long",(G7-V7)*H7*I7,(V7-G7)*H7*I7),"") -> 57845000 | AD7: =IFERROR(IF(OR(AF7="STOP LOSS HIT",AF7="TAKE PROFIT HIT"),AG7,""),"") -> 273.5 | AE7: =IFERROR(IF(E7="Long",(IF(AND(B7="Closed",AD7<>""),AD7,O7)-G7)/G7,(G7-IF(AND(B7="Closed",AD7<>""),AD7,O7))/G7),"") -> -0.018059096 | AF7: =IFERROR(IF(OR(V7="",W7=""),"No SL/TP",IF(E7="Long",IF(O7<=V7,"STOP LOSS HIT",IF(O7>=W7,"TAKE PROFIT HIT",IF(B7="Closed","CLOSED","Active"))),IF(O7>=V7,"STOP LOSS HIT",IF(O7<=W7,"TAKE PROFIT HIT",IF(B7="Closed","CLOSED","Active"))))),"—") -> STOP LOSS HIT | AG7: =IFERROR(IF(E7="Long",IF(O7<=V7,V7,IF(O7>=W7,W7,"")),IF(O7>=V7,V7,IF(O7<=W7,W7,""))),"") -> 273.5 | AH7: =IFERROR(IF(B7<>"Open","—",IF(E7="Long",G7*(1-1/I7),G7*(1+1/I7))),"—") -> —
A8: =IFERROR(ROW()-5,"") -> 3 | B8: Closed | C8: Forex | D8: AUD/USD | E8: Short | F8: 46090 | G8: 0.7798 | H8: 300000000 | I8: 20 | J8: =IFERROR(1/I8,"") -> 0.05 | K8: =IFERROR(G8*H8*I8,"") -> 4678800000 | L8: =IFERROR(G8*H8,"") -> 233940000 | M8: 0.5 | N8: =IFERROR(IF(B8<>"Open","—",IF((G8*H8+Q8)<=0,"LIQUIDATION",IF((G8*H8+Q8)/(G8*H8)<=M8,"WARNING","OK"))),"—") -> — | O8: 0.777 | P8: =IFERROR((IF(AND(B8="Closed",AD8<>""),AD8,O8))*H8,"") -> 233100000 | Q8: =IFERROR(IF(E8="Long",(IF(AND(B8="Closed",AD8<>""),AD8,O8)-G8)*H8*I8,(G8-IF(AND(B8="Closed",AD8<>""),AD8,O8))*H8*I8),"") -> 16800000 | R8: =IFERROR(Q8/(G8*H8),"") -> 0.071813285 | S8: =IFERROR(L8/(IFERROR(LOOKUP(2,1/('Transaction Log'!H5:H106<>""),'Transaction Log'!H5:H106),0)),"") -> 0.11411707 | T8: 46092 | U8: =IFERROR(IF(B8="Closed",T8-F8,TODAY()-F8),"") -> 2 | V8: 0.777 | W8: 0.774 | X8: =IFERROR(IF(OR(V8="",I8=""),"—",IF(E8="Long",(G8-V8)*H8*I8,(V8-G8)*H8*I8)),"—") -> -16800000 | Y8: =IFERROR(IF(OR(V8="",G8=""),"—",IF(E8="Long",(G8-V8)/G8,(V8-G8)/G8)),"—") -> -0.0035906643 | Z8: =IFERROR(IF(OR(W8="",I8=""),"—",IF(E8="Long",(W8-G8)*H8*I8,(G8-W8)*H8*I8)),"—") -> 34800000 | AA8: =IFERROR(IF(OR(W8="",G8=""),"—",IF(E8="Long",(W8-G8)/G8,(G8-W8)/G8)),"—") -> 0.0074378046 | AB8: Position volume added | AC8: =IFERROR(IF(E8="Long",(G8-V8)*H8*I8,(V8-G8)*H8*I8),"") -> -16800000 | AD8: =IFERROR(IF(OR(AF8="STOP LOSS HIT",AF8="TAKE PROFIT HIT"),AG8,""),"") -> 0.777 | AE8: =IFERROR(IF(E8="Long",(IF(AND(B8="Closed",AD8<>""),AD8,O8)-G8)/G8,(G8-IF(AND(B8="Closed",AD8<>""),AD8,O8))/G8),"") -> 0.0035906643 | AF8: =IFERROR(IF(OR(V8="",W8=""),"No SL/TP",IF(E8="Long",IF(O8<=V8,"STOP LOSS HIT",IF(O8>=W8,"TAKE PROFIT HIT",IF(B8="Closed","CLOSED","Active"))),IF(O8>=V8,"STOP LOSS HIT",IF(O8<=W8,"TAKE PROFIT HIT",IF(B8="Closed","CLOSED","Active"))))),"—") -> STOP LOSS HIT | AG8: =IFERROR(IF(E8="Long",IF(O8<=V8,V8,IF(O8>=W8,W8,"")),IF(O8>=V8,V8,IF(O8<=W8,W8,""))),"") -> 0.777 | AH8: =IFERROR(IF(B8<>"Open","—",IF(E8="Long",G8*(1-1/I8),G8*(1+1/I8))),"—") -> —
A9: =IFERROR(ROW()-5,"") -> 4 | B9: Closed | C9: Futures | D9: Gold | E9: Long | F9: 46090 | G9: 5106.38 | H9: 160000 | I9: 20 | J9: =IFERROR(1/I9,"") -> 0.05 | K9: =IFERROR(G9*H9*I9,"") -> 16340416000 | L9: =IFERROR(G9*H9,"") -> 817020800 | M9: 0.5 | N9: =IFERROR(IF(B9<>"Open","—",IF((G9*H9+Q9)<=0,"LIQUIDATION",IF((G9*H9+Q9)/(G9*H9)<=M9,"WARNING","OK"))),"—") -> — | O9: 5234 | P9: =IFERROR((IF(AND(B9="Closed",AD9<>""),AD9,O9))*H9,"") -> 837440000 | Q9: =IFERROR(IF(E9="Long",(IF(AND(B9="Closed",AD9<>""),AD9,O9)-G9)*H9*I9,(G9-IF(AND(B9="Closed",AD9<>""),AD9,O9))*H9*I9),"") -> 4.08384e+08 | R9: =IFERROR(Q9/(G9*H9),"") -> 0.49984529 | S9: =IFERROR(L9/(IFERROR(LOOKUP(2,1/('Transaction Log'!H5:H106<>""),'Transaction Log'!H5:H106),0)),"") -> 0.39854673 | T9: 46091 | U9: =IFERROR(IF(B9="Closed",T9-F9,TODAY()-F9),"") -> 1 | V9: 5058 | W9: 5234 | X9: =IFERROR(IF(OR(V9="",I9=""),"—",IF(E9="Long",(G9-V9)*H9*I9,(V9-G9)*H9*I9)),"—") -> 1.54816e+08 | Y9: =IFERROR(IF(OR(V9="",G9=""),"—",IF(E9="Long",(G9-V9)/G9,(V9-G9)/G9)),"—") -> 0.0094744222 | Z9: =IFERROR(IF(OR(W9="",I9=""),"—",IF(E9="Long",(W9-G9)*H9*I9,(G9-W9)*H9*I9)),"—") -> 4.08384e+08 | AA9: =IFERROR(IF(OR(W9="",G9=""),"—",IF(E9="Long",(W9-G9)/G9,(G9-W9)/G9)),"—") -> 0.024992265 | AB9: Additional position Long on Gold market opening Monday | AC9: =IFERROR(IF(E9="Long",(G9-V9)*H9*I9,(V9-G9)*H9*I9),"") -> 1.54816e+08 | AD9: =IFERROR(IF(OR(AF9="STOP LOSS HIT",AF9="TAKE PROFIT HIT"),AG9,""),"") -> 5234 | AE9: =IFERROR(IF(E9="Long",(IF(AND(B9="Closed",AD9<>""),AD9,O9)-G9)/G9,(G9-IF(AND(B9="Closed",AD9<>""),AD9,O9))/G9),"") -> 0.024992265 | AF9: =IFERROR(IF(OR(V9="",W9=""),"No SL/TP",IF(E9="Long",IF(O9<=V9,"STOP LOSS HIT",IF(O9>=W9,"TAKE PROFIT HIT",IF(B9="Closed","CLOSED","Active"))),IF(O9>=V9,"STOP LOSS HIT",IF(O9<=W9,"TAKE PROFIT HIT",IF(B9="Closed","CLOSED","Active"))))),"—") -> TAKE PROFIT HIT | AG9: =IFERROR(IF(E9="Long",IF(O9<=V9,V9,IF(O9>=W9,W9,"")),IF(O9>=V9,V9,IF(O9<=W9,W9,""))),"") -> 5234 | AH9: =IFERROR(IF(B9<>"Open","—",IF(E9="Long",G9*(1-1/I9),G9*(1+1/I9))),"—") -> —
A10: =IFERROR(ROW()-5,"") -> 5 | B10: Closed | C10: Forex | D10: AUD/USD | E10: Short | F10: 46090 | G10: 0.77852 | H10: 500000000 | I10: 15 | J10: =IFERROR(1/I10,"") -> 0.066666667 | K10: =IFERROR(G10*H10*I10,"") -> 5838900000 | L10: =IFERROR(G10*H10,"") -> 389260000 | M10: 0.5 | N10: =IFERROR(IF(B10<>"Open","—",IF((G10*H10+Q10)<=0,"LIQUIDATION",IF((G10*H10+Q10)/(G10*H10)<=M10,"WARNING","OK"))),"—") -> — | O10: 0.7759 | P10: =IFERROR((IF(AND(B10="Closed",AD10<>""),AD10,O10))*H10,"") -> 387950000 | Q10: =IFERROR(IF(E10="Long",(IF(AND(B10="Closed",AD10<>""),AD10,O10)-G10)*H10*I10,(G10-IF(AND(B10="Closed",AD10<>""),AD10,O10))*H10*I10),"") -> 19650000 | R10: =IFERROR(Q10/(G10*H10),"") -> 0.050480399 | S10: =IFERROR(L10/(IFERROR(LOOKUP(2,1/('Transaction Log'!H5:H106<>""),'Transaction Log'!H5:H106),0)),"") -> 0.18988293 | T10: 46091 | U10: =IFERROR(IF(B10="Closed",T10-F10,TODAY()-F10),"") -> 1 | V10: 0.782 | W10: 0.7759 | X10: =IFERROR(IF(OR(V10="",I10=""),"—",IF(E10="Long",(G10-V10)*H10*I10,(V10-G10)*H10*I10)),"—") -> 26100000 | Y10: =IFERROR(IF(OR(V10="",G10=""),"—",IF(E10="Long",(G10-V10)/G10,(V10-G10)/G10)),"—") -> 0.00447002 | Z10: =IFERROR(IF(OR(W10="",I10=""),"—",IF(E10="Long",(W10-G10)*H10*I10,(G10-W10)*H10*I10)),"—") -> 19650000 | AA10: =IFERROR(IF(OR(W10="",G10=""),"—",IF(E10="Long",(W10-G10)/G10,(G10-W10)/G10)),"—") -> 0.0033653599 | AB10: Inverse relationship with gold complementary trade | AC10: =IFERROR(IF(E10="Long",(G10-V10)*H10*I10,(V10-G10)*H10*I10),"") -> 26100000 | AD10: =IFERROR(IF(OR(AF10="STOP LOSS HIT",AF10="TAKE PROFIT HIT"),AG10,""),"") -> 0.7759 | AE10: =IFERROR(IF(E10="Long",(IF(AND(B10="Closed",AD10<>""),AD10,O10)-G10)/G10,(G10-IF(AND(B10="Closed",AD10<>""),AD10,O10))/G10),"") -> 0.0033653599 | AF10: =IFERROR(IF(OR(V10="",W10=""),"No SL/TP",IF(E10="Long",IF(O10<=V10,"STOP LOSS HIT",IF(O10>=W10,"TAKE PROFIT HIT",IF(B10="Closed","CLOSED","Active"))),IF(O10>=V10,"STOP LOSS HIT",IF(O10<=W10,"TAKE PROFIT HIT",IF(B10="Closed","CLOSED","Active"))))),"—") -> TAKE PROFIT HIT | AG10: =IFERROR(IF(E10="Long",IF(O10<=V10,V10,IF(O10>=W10,W10,"")),IF(O10>=V10,V10,IF(O10<=W10,W10,""))),"") -> 0.7759 | AH10: =IFERROR(IF(B10<>"Open","—",IF(E10="Long",G10*(1-1/I10),G10*(1+1/I10))),"—") -> —
A11: =IFERROR(ROW()-5,"") -> 6 | B11: Closed | C11: Futures | D11: Gold | E11: Long | F11: 46087 | G11: 5078 | H11: 140000 | I11: 20 | J11: =IFERROR(1/I11,"") -> 0.05 | K11: =IFERROR(G11*H11*I11,"") -> 14218400000 | L11: =IFERROR(G11*H11,"") -> 710920000 | M11: 0.5 | N11: =IFERROR(IF(B11<>"Open","—",IF((G11*H11+Q11)<=0,"LIQUIDATION",IF((G11*H11+Q11)/(G11*H11)<=M11,"WARNING","OK"))),"—") -> — | O11: 5172 | P11: =IFERROR((IF(AND(B11="Closed",AD11<>""),AD11,O11))*H11,"") -> 724080000 | Q11: =IFERROR(IF(E11="Long",(IF(AND(B11="Closed",AD11<>""),AD11,O11)-G11)*H11*I11,(G11-IF(AND(B11="Closed",AD11<>""),AD11,O11))*H11*I11),"") -> 263200000 | R11: =IFERROR(Q11/(G11*H11),"") -> 0.3702245 | S11: =IFERROR(L11/(IFERROR(LOOKUP(2,1/('Transaction Log'!H5:H106<>""),'Transaction Log'!H5:H106),0)),"") -> 0.34679024 | T11: 46087 | U11: =IFERROR(IF(B11="Closed",T11-F11,TODAY()-F11),"") -> 0 | V11: 5050 | W11: 5172 | X11: =IFERROR(IF(OR(V11="",I11=""),"—",IF(E11="Long",(G11-V11)*H11*I11,(V11-G11)*H11*I11)),"—") -> 78400000 | Y11: =IFERROR(IF(OR(V11="",G11=""),"—",IF(E11="Long",(G11-V11)/G11,(V11-G11)/G11)),"—") -> 0.0055139819 | Z11: =IFERROR(IF(OR(W11="",I11=""),"—",IF(E11="Long",(W11-G11)*H11*I11,(G11-W11)*H11*I11)),"—") -> 263200000 | AA11: =IFERROR(IF(OR(W11="",G11=""),"—",IF(E11="Long",(W11-G11)/G11,(G11-W11)/G11)),"—") -> 0.018511225 | AB11: Geopo-leads to investing in safe assets HOLD | AC11: =IFERROR(IF(E11="Long",(G11-V11)*H11*I11,(V11-G11)*H11*I11),"") -> 78400000 | AD11: =IFERROR(IF(OR(AF11="STOP LOSS HIT",AF11="TAKE PROFIT HIT"),AG11,""),"") -> 5172 | AE11: =IFERROR(IF(E11="Long",(IF(AND(B11="Closed",AD11<>""),AD11,O11)-G11)/G11,(G11-IF(AND(B11="Closed",AD11<>""),AD11,O11))/G11),"") -> 0.018511225 | AF11: =IFERROR(IF(OR(V11="",W11=""),"No SL/TP",IF(E11="Long",IF(O11<=V11,"STOP LOSS HIT",IF(O11>=W11,"TAKE PROFIT HIT",IF(B11="Closed","CLOSED","Active"))),IF(O11>=V11,"STOP LOSS HIT",IF(O11<=W11,"TAKE PROFIT HIT",IF(B11="Closed","CLOSED","Active"))))),"—") -> TAKE PROFIT HIT | AG11: =IFERROR(IF(E11="Long",IF(O11<=V11,V11,IF(O11>=W11,W11,"")),IF(O11>=V11,V11,IF(O11<=W11,W11,""))),"") -> 5172 | AH11: =IFERROR(IF(B11<>"Open","—",IF(E11="Long",G11*(1-1/I11),G11*(1+1/I11))),"—") -> —
A12: =IFERROR(ROW()-5,"") -> 7 | B12: Closed | C12: Crypto | D12: BTC | E12: Long | F12: 46087 | G12: 70509.74 | H12: 15000 | I12: 20 | J12: =IFERROR(1/I12,"") -> 0.05 | K12: =IFERROR(G12*H12*I12,"") -> 2.1152922e+10 | L12: =IFERROR(G12*H12,"") -> 1.0576461e+09 | M12: 0.5 | N12: =IFERROR(IF(B12<>"Open","—",IF((G12*H12+Q12)<=0,"LIQUIDATION",IF((G12*H12+Q12)/(G12*H12)<=M12,"WARNING","OK"))),"—") -> — | O12: 71230 | P12: =IFERROR((IF(AND(B12="Closed",AD12<>""),AD12,O12))*H12,"") -> 1068450000 | Q12: =IFERROR(IF(E12="Long",(IF(AND(B12="Closed",AD12<>""),AD12,O12)-G12)*H12*I12,(G12-IF(AND(B12="Closed",AD12<>""),AD12,O12))*H12*I12),"") -> 2.16078e+08 | R12: =IFERROR(Q12/(G12*H12),"") -> 0.20430085 | S12: =IFERROR(L12/(IFERROR(LOOKUP(2,1/('Transaction Log'!H5:H106<>""),'Transaction Log'!H5:H106),0)),"") -> 0.51592493 | T12: 46087 | U12: =IFERROR(IF(B12="Closed",T12-F12,TODAY()-F12),"") -> 0 | V12: 68950 | W12: 71230 | X12: =IFERROR(IF(OR(V12="",I12=""),"—",IF(E12="Long",(G12-V12)*H12*I12,(V12-G12)*H12*I12)),"—") -> 4.67922e+08 | Y12: =IFERROR(IF(OR(V12="",G12=""),"—",IF(E12="Long",(G12-V12)/G12,(V12-G12)/G12)),"—") -> 0.022120915 | Z12: =IFERROR(IF(OR(W12="",I12=""),"—",IF(E12="Long",(W12-G12)*H12*I12,(G12-W12)*H12*I12)),"—") -> 2.16078e+08 | AA12: =IFERROR(IF(OR(W12="",G12=""),"—",IF(E12="Long",(W12-G12)/G12,(G12-W12)/G12)),"—") -> 0.010215043 | AB12: BTC big drawback, must restore resistance and buy volume rallying up price | AC12: =IFERROR(IF(E12="Long",(G12-V12)*H12*I12,(V12-G12)*H12*I12),"") -> 4.67922e+08 | AD12: =IFERROR(IF(OR(AF12="STOP LOSS HIT",AF12="TAKE PROFIT HIT"),AG12,""),"") -> 71230 | AE12: =IFERROR(IF(E12="Long",(IF(AND(B12="Closed",AD12<>""),AD12,O12)-G12)/G12,(G12-IF(AND(B12="Closed",AD12<>""),AD12,O12))/G12),"") -> 0.010215043 | AF12: =IFERROR(IF(OR(V12="",W12=""),"No SL/TP",IF(E12="Long",IF(O12<=V12,"STOP LOSS HIT",IF(O12>=W12,"TAKE PROFIT HIT",IF(B12="Closed","CLOSED","Active"))),IF(O12>=V12,"STOP LOSS HIT",IF(O12<=W12,"TAKE PROFIT HIT",IF(B12="Closed","CLOSED","Active"))))),"—") -> TAKE PROFIT HIT | AG12: =IFERROR(IF(E12="Long",IF(O12<=V12,V12,IF(O12>=W12,W12,"")),IF(O12>=V12,V12,IF(O12<=W12,W12,""))),"") -> 71230 | AH12: =IFERROR(IF(B12<>"Open","—",IF(E12="Long",G12*(1-1/I12),G12*(1+1/I12))),"—") -> —
A13: =IFERROR(ROW()-5,"") -> 8 | B13: Closed | C13: Futures | D13: Oil | E13: Long | F13: 46087 | G13: 78.585 | H13: 500000 | I13: 10 | J13: =IFERROR(1/I13,"") -> 0.1 | K13: =IFERROR(G13*H13*I13,"") -> 392925000 | L13: =IFERROR(G13*H13,"") -> 39292500 | M13: 0.5 | N13: =IFERROR(IF(B13<>"Open","—",IF((G13*H13+Q13)<=0,"LIQUIDATION",IF((G13*H13+Q13)/(G13*H13)<=M13,"WARNING","OK"))),"—") -> — | O13: 86.28 | P13: =IFERROR((IF(AND(B13="Closed",AD13<>""),AD13,O13))*H13,"") -> 43140000 | Q13: =IFERROR(IF(E13="Long",(IF(AND(B13="Closed",AD13<>""),AD13,O13)-G13)*H13*I13,(G13-IF(AND(B13="Closed",AD13<>""),AD13,O13))*H13*I13),"") -> 38475000 | R13: =IFERROR(Q13/(G13*H13),"") -> 0.9791945 | S13: =IFERROR(L13/(IFERROR(LOOKUP(2,1/('Transaction Log'!H5:H106<>""),'Transaction Log'!H5:H106),0)),"") -> 0.019167073 | T13: 46087 | U13: =IFERROR(IF(B13="Closed",T13-F13,TODAY()-F13),"") -> 0 | V13: 76.35 | W13: 86.28 | X13: =IFERROR(IF(OR(V13="",I13=""),"—",IF(E13="Long",(G13-V13)*H13*I13,(V13-G13)*H13*I13)),"—") -> 11175000 | Y13: =IFERROR(IF(OR(V13="",G13=""),"—",IF(E13="Long",(G13-V13)/G13,(V13-G13)/G13)),"—") -> 0.028440542 | Z13: =IFERROR(IF(OR(W13="",I13=""),"—",IF(E13="Long",(W13-G13)*H13*I13,(G13-W13)*H13*I13)),"—") -> 38475000 | AA13: =IFERROR(IF(OR(W13="",G13=""),"—",IF(E13="Long",(W13-G13)/G13,(G13-W13)/G13)),"—") -> 0.09791945 | AB13: Continued burden on closing of straight of Hormuz | AC13: =IFERROR(IF(E13="Long",(G13-V13)*H13*I13,(V13-G13)*H13*I13),"") -> 11175000 | AD13: =IFERROR(IF(OR(AF13="STOP LOSS HIT",AF13="TAKE PROFIT HIT"),AG13,""),"") -> 86.28 | AE13: =IFERROR(IF(E13="Long",(IF(AND(B13="Closed",AD13<>""),AD13,O13)-G13)/G13,(G13-IF(AND(B13="Closed",AD13<>""),AD13,O13))/G13),"") -> 0.09791945 | AF13: =IFERROR(IF(OR(V13="",W13=""),"No SL/TP",IF(E13="Long",IF(O13<=V13,"STOP LOSS HIT",IF(O13>=W13,"TAKE PROFIT HIT",IF(B13="Closed","CLOSED","Active"))),IF(O13>=V13,"STOP LOSS HIT",IF(O13<=W13,"TAKE PROFIT HIT",IF(B13="Closed","CLOSED","Active"))))),"—") -> TAKE PROFIT HIT | AG13: =IFERROR(IF(E13="Long",IF(O13<=V13,V13,IF(O13>=W13,W13,"")),IF(O13>=V13,V13,IF(O13<=W13,W13,""))),"") -> 86.28 | AH13: =IFERROR(IF(B13<>"Open","—",IF(E13="Long",G13*(1-1/I13),G13*(1+1/I13))),"—") -> —
A14: =IFERROR(ROW()-5,"") -> 9 | B14: Closed | C14: Crypto | D14: BTC | E14: Short | F14: 46087 | G14: 70755.2 | H14: 7200 | I14: 20 | J14: =IFERROR(1/I14,"") -> 0.05 | K14: =IFERROR(G14*H14*I14,"") -> 10188748800 | L14: =IFERROR(G14*H14,"") -> 509437440 | M14: 0.5 | N14: =IFERROR(IF(B14<>"Open","—",IF((G14*H14+Q14)<=0,"LIQUIDATION",IF((G14*H14+Q14)/(G14*H14)<=M14,"WARNING","OK"))),"—") -> — | O14: 69975 | P14: =IFERROR((IF(AND(B14="Closed",AD14<>""),AD14,O14))*H14,"") -> 503820000 | Q14: =IFERROR(IF(E14="Long",(IF(AND(B14="Closed",AD14<>""),AD14,O14)-G14)*H14*I14,(G14-IF(AND(B14="Closed",AD14<>""),AD14,O14))*H14*I14),"") -> 1.123488e+08 | R14: =IFERROR(Q14/(G14*H14),"") -> 0.22053503 | S14: =IFERROR(L14/(IFERROR(LOOKUP(2,1/('Transaction Log'!H5:H106<>""),'Transaction Log'!H5:H106),0)),"") -> 0.24850607 | T14: 46087 | U14: =IFERROR(IF(B14="Closed",T14-F14,TODAY()-F14),"") -> 0 | V14: 71445 | W14: 69975 | X14: =IFERROR(IF(OR(V14="",I14=""),"—",IF(E14="Long",(G14-V14)*H14*I14,(V14-G14)*H14*I14)),"—") -> 99331200 | Y14: =IFERROR(IF(OR(V14="",G14=""),"—",IF(E14="Long",(G14-V14)/G14,(V14-G14)/G14)),"—") -> 0.0097491068 | Z14: =IFERROR(IF(OR(W14="",I14=""),"—",IF(E14="Long",(W14-G14)*H14*I14,(G14-W14)*H14*I14)),"—") -> 1.123488e+08 | AA14: =IFERROR(IF(OR(W14="",G14=""),"—",IF(E14="Long",(W14-G14)/G14,(G14-W14)/G14)),"—") -> 0.011026751 | AB14: BTC Bear swing sentiment - projected 40k support level | AC14: =IFERROR(IF(E14="Long",(G14-V14)*H14*I14,(V14-G14)*H14*I14),"") -> 99331200 | AD14: =IFERROR(IF(OR(AF14="STOP LOSS HIT",AF14="TAKE PROFIT HIT"),AG14,""),"") -> 69975 | AE14: =IFERROR(IF(E14="Long",(IF(AND(B14="Closed",AD14<>""),AD14,O14)-G14)/G14,(G14-IF(AND(B14="Closed",AD14<>""),AD14,O14))/G14),"") -> 0.011026751 | AF14: =IFERROR(IF(OR(V14="",W14=""),"No SL/TP",IF(E14="Long",IF(O14<=V14,"STOP LOSS HIT",IF(O14>=W14,"TAKE PROFIT HIT",IF(B14="Closed","CLOSED","Active"))),IF(O14>=V14,"STOP LOSS HIT",IF(O14<=W14,"TAKE PROFIT HIT",IF(B14="Closed","CLOSED","Active"))))),"—") -> TAKE PROFIT HIT | AG14: =IFERROR(IF(E14="Long",IF(O14<=V14,V14,IF(O14>=W14,W14,"")),IF(O14>=V14,V14,IF(O14<=W14,W14,""))),"") -> 69975 | AH14: =IFERROR(IF(B14<>"Open","—",IF(E14="Long",G14*(1-1/I14),G14*(1+1/I14))),"—") -> —
A15: =IFERROR(ROW()-5,"") -> 10 | B15: Closed | C15: Futures | D15: Oil | E15: Long | F15: 46087 | G15: 85.43 | H15: 15000 | I15: 20 | J15: =IFERROR(1/I15,"") -> 0.05 | K15: =IFERROR(G15*H15*I15,"") -> 25629000 | L15: =IFERROR(G15*H15,"") -> 1281450 | M15: 0.5 | N15: =IFERROR(IF(B15<>"Open","—",IF((G15*H15+Q15)<=0,"LIQUIDATION",IF((G15*H15+Q15)/(G15*H15)<=M15,"WARNING","OK"))),"—") -> — | O15: 90.16 | P15: =IFERROR((IF(AND(B15="Closed",AD15<>""),AD15,O15))*H15,"") -> 1352400 | Q15: =IFERROR(IF(E15="Long",(IF(AND(B15="Closed",AD15<>""),AD15,O15)-G15)*H15*I15,(G15-IF(AND(B15="Closed",AD15<>""),AD15,O15))*H15*I15),"") -> 1419000 | R15: =IFERROR(Q15/(G15*H15),"") -> 1.1073393 | S15: =IFERROR(L15/(IFERROR(LOOKUP(2,1/('Transaction Log'!H5:H106<>""),'Transaction Log'!H5:H106),0)),"") -> 0.00062509756 | T15: 46088 | U15: =IFERROR(IF(B15="Closed",T15-F15,TODAY()-F15),"") -> 1 | V15: 84.78 | W15: 90.16 | X15: =IFERROR(IF(OR(V15="",I15=""),"—",IF(E15="Long",(G15-V15)*H15*I15,(V15-G15)*H15*I15)),"—") -> 195000 | Y15: =IFERROR(IF(OR(V15="",G15=""),"—",IF(E15="Long",(G15-V15)/G15,(V15-G15)/G15)),"—") -> 0.0076085684 | Z15: =IFERROR(IF(OR(W15="",I15=""),"—",IF(E15="Long",(W15-G15)*H15*I15,(G15-W15)*H15*I15)),"—") -> 1419000 | AA15: =IFERROR(IF(OR(W15="",G15=""),"—",IF(E15="Long",(W15-G15)/G15,(G15-W15)/G15)),"—") -> 0.055366967 | AB15: New Long Hold on Oil until TP, distanced SL to avoid volatility | AC15: =IFERROR(IF(E15="Long",(G15-V15)*H15*I15,(V15-G15)*H15*I15),"") -> 195000 | AD15: =IFERROR(IF(OR(AF15="STOP LOSS HIT",AF15="TAKE PROFIT HIT"),AG15,""),"") -> 90.16 | AE15: =IFERROR(IF(E15="Long",(IF(AND(B15="Closed",AD15<>""),AD15,O15)-G15)/G15,(G15-IF(AND(B15="Closed",AD15<>""),AD15,O15))/G15),"") -> 0.055366967 | AF15: =IFERROR(IF(OR(V15="",W15=""),"No SL/TP",IF(E15="Long",IF(O15<=V15,"STOP LOSS HIT",IF(O15>=W15,"TAKE PROFIT HIT",IF(B15="Closed","CLOSED","Active"))),IF(O15>=V15,"STOP LOSS HIT",IF(O15<=W15,"TAKE PROFIT HIT",IF(B15="Closed","CLOSED","Active"))))),"—") -> TAKE PROFIT HIT | AG15: =IFERROR(IF(E15="Long",IF(O15<=V15,V15,IF(O15>=W15,W15,"")),IF(O15>=V15,V15,IF(O15<=W15,W15,""))),"") -> 90.16 | AH15: =IFERROR(IF(B15<>"Open","—",IF(E15="Long",G15*(1-1/I15),G15*(1+1/I15))),"—") -> —
A16: =IFERROR(ROW()-5,"") -> 11 | B16: Closed | C16: Futures | D16: Oil | E16: Long | F16: 46087 | G16: 87.13 | H16: 25000 | I16: 10 | J16: =IFERROR(1/I16,"") -> 0.1 | K16: =IFERROR(G16*H16*I16,"") -> 21782500 | L16: =IFERROR(G16*H16,"") -> 2178250 | M16: 0.5 | N16: =IFERROR(IF(B16<>"Open","—",IF((G16*H16+Q16)<=0,"LIQUIDATION",IF((G16*H16+Q16)/(G16*H16)<=M16,"WARNING","OK"))),"—") -> — | O16: 96.49 | P16: =IFERROR((IF(AND(B16="Closed",AD16<>""),AD16,O16))*H16,"") -> 2412250 | Q16: =IFERROR(IF(E16="Long",(IF(AND(B16="Closed",AD16<>""),AD16,O16)-G16)*H16*I16,(G16-IF(AND(B16="Closed",AD16<>""),AD16,O16))*H16*I16),"") -> 2340000 | R16: =IFERROR(Q16/(G16*H16),"") -> 1.0742569 | S16: =IFERROR(L16/(IFERROR(LOOKUP(2,1/('Transaction Log'!H5:H106<>""),'Transaction Log'!H5:H106),0)),"") -> 0.001062561 | T16: 46090 | U16: =IFERROR(IF(B16="Closed",T16-F16,TODAY()-F16),"") -> 3 | V16: 84.24 | W16: 96.49 | X16: =IFERROR(IF(OR(V16="",I16=""),"—",IF(E16="Long",(G16-V16)*H16*I16,(V16-G16)*H16*I16)),"—") -> 722500 | Y16: =IFERROR(IF(OR(V16="",G16=""),"—",IF(E16="Long",(G16-V16)/G16,(V16-G16)/G16)),"—") -> 0.033168828 | Z16: =IFERROR(IF(OR(W16="",I16=""),"—",IF(E16="Long",(W16-G16)*H16*I16,(G16-W16)*H16*I16)),"—") -> 2340000 | AA16: =IFERROR(IF(OR(W16="",G16=""),"—",IF(E16="Long",(W16-G16)/G16,(G16-W16)/G16)),"—") -> 0.10742569 | AB16: Added position to amplify gains, higher TP lower Leverage | AC16: =IFERROR(IF(E16="Long",(G16-V16)*H16*I16,(V16-G16)*H16*I16),"") -> 722500 | AD16: =IFERROR(IF(OR(AF16="STOP LOSS HIT",AF16="TAKE PROFIT HIT"),AG16,""),"") -> 96.49 | AE16: =IFERROR(IF(E16="Long",(IF(AND(B16="Closed",AD16<>""),AD16,O16)-G16)/G16,(G16-IF(AND(B16="Closed",AD16<>""),AD16,O16))/G16),"") -> 0.10742569 | AF16: =IFERROR(IF(OR(V16="",W16=""),"No SL/TP",IF(E16="Long",IF(O16<=V16,"STOP LOSS HIT",IF(O16>=W16,"TAKE PROFIT HIT",IF(B16="Closed","CLOSED","Active"))),IF(O16>=V16,"STOP LOSS HIT",IF(O16<=W16,"TAKE PROFIT HIT",IF(B16="Closed","CLOSED","Active"))))),"—") -> TAKE PROFIT HIT | AG16: =IFERROR(IF(E16="Long",IF(O16<=V16,V16,IF(O16>=W16,W16,"")),IF(O16>=V16,V16,IF(O16<=W16,W16,""))),"") -> 96.49 | AH16: =IFERROR(IF(B16<>"Open","—",IF(E16="Long",G16*(1-1/I16),G16*(1+1/I16))),"—") -> —
A17: =IFERROR(ROW()-5,"") -> 12 | B17: Closed | C17: Index | D17: Nikkei 225 | E17: Short | F17: 46087 | G17: 22748.986 | H17: 18000 | I17: 10 | J17: =IFERROR(1/I17,"") -> 0.1 | K17: =IFERROR(G17*H17*I17,"") -> 4094817480 | L17: =IFERROR(G17*H17,"") -> 409481748 | M17: 0.5 | N17: =IFERROR(IF(B17<>"Open","—",IF((G17*H17+Q17)<=0,"LIQUIDATION",IF((G17*H17+Q17)/(G17*H17)<=M17,"WARNING","OK"))),"—") -> — | O17: 22387.679 | P17: =IFERROR((IF(AND(B17="Closed",AD17<>""),AD17,O17))*H17,"") -> 402978222 | Q17: =IFERROR(IF(E17="Long",(IF(AND(B17="Closed",AD17<>""),AD17,O17)-G17)*H17*I17,(G17-IF(AND(B17="Closed",AD17<>""),AD17,O17))*H17*I17),"") -> 65035260 | R17: =IFERROR(Q17/(G17*H17),"") -> 0.15882334 | S17: =IFERROR(L17/(IFERROR(LOOKUP(2,1/('Transaction Log'!H5:H106<>""),'Transaction Log'!H5:H106),0)),"") -> 0.19974719 | T17: 46090 | U17: =IFERROR(IF(B17="Closed",T17-F17,TODAY()-F17),"") -> 3 | V17: 23258 | W17: 22324 | X17: =IFERROR(IF(OR(V17="",I17=""),"—",IF(E17="Long",(G17-V17)*H17*I17,(V17-G17)*H17*I17)),"—") -> 91622520 | Y17: =IFERROR(IF(OR(V17="",G17=""),"—",IF(E17="Long",(G17-V17)/G17,(V17-G17)/G17)),"—") -> 0.022375239 | Z17: =IFERROR(IF(OR(W17="",I17=""),"—",IF(E17="Long",(W17-G17)*H17*I17,(G17-W17)*H17*I17)),"—") -> 76497480 | AA17: =IFERROR(IF(OR(W17="",G17=""),"—",IF(E17="Long",(W17-G17)/G17,(G17-W17)/G17)),"—") -> 0.018681536 | AB17: Growing fear in US market over war | AC17: =IFERROR(IF(E17="Long",(G17-V17)*H17*I17,(V17-G17)*H17*I17),"") -> 91622520 | AD17: =IFERROR(IF(OR(AF17="STOP LOSS HIT",AF17="TAKE PROFIT HIT"),AG17,""),"") | AE17: =IFERROR(IF(E17="Long",(IF(AND(B17="Closed",AD17<>""),AD17,O17)-G17)/G17,(G17-IF(AND(B17="Closed",AD17<>""),AD17,O17))/G17),"") -> 0.015882334 | AF17: =IFERROR(IF(OR(V17="",W17=""),"No SL/TP",IF(E17="Long",IF(O17<=V17,"STOP LOSS HIT",IF(O17>=W17,"TAKE PROFIT HIT",IF(B17="Closed","CLOSED","Active"))),IF(O17>=V17,"STOP LOSS HIT",IF(O17<=W17,"TAKE PROFIT HIT",IF(B17="Closed","CLOSED","Active"))))),"—") -> CLOSED | AG17: =IFERROR(IF(E17="Long",IF(O17<=V17,V17,IF(O17>=W17,W17,"")),IF(O17>=V17,V17,IF(O17<=W17,W17,""))),"") | AH17: =IFERROR(IF(B17<>"Open","—",IF(E17="Long",G17*(1-1/I17),G17*(1+1/I17))),"—") -> —
A18: =IFERROR(ROW()-5,"") -> 13 | B18: Closed | C18: Forex | D18: AUD/USD | E18: Short | F18: 46087 | G18: 0.7817 | H18: 400000000 | I18: 10 | J18: =IFERROR(1/I18,"") -> 0.1 | K18: =IFERROR(G18*H18*I18,"") -> 3126800000 | L18: =IFERROR(G18*H18,"") -> 312680000 | M18: 0.5 | N18: =IFERROR(IF(B18<>"Open","—",IF((G18*H18+Q18)<=0,"LIQUIDATION",IF((G18*H18+Q18)/(G18*H18)<=M18,"WARNING","OK"))),"—") -> — | O18: 0.776 | P18: =IFERROR((IF(AND(B18="Closed",AD18<>""),AD18,O18))*H18,"") -> 310400000 | Q18: =IFERROR(IF(E18="Long",(IF(AND(B18="Closed",AD18<>""),AD18,O18)-G18)*H18*I18,(G18-IF(AND(B18="Closed",AD18<>""),AD18,O18))*H18*I18),"") -> 22800000 | R18: =IFERROR(Q18/(G18*H18),"") -> 0.072917999 | S18: =IFERROR(L18/(IFERROR(LOOKUP(2,1/('Transaction Log'!H5:H106<>""),'Transaction Log'!H5:H106),0)),"") -> 0.15252683 | T18: 46087 | U18: =IFERROR(IF(B18="Closed",T18-F18,TODAY()-F18),"") -> 0 | V18: 0.7858 | W18: 0.776 | X18: =IFERROR(IF(OR(V18="",I18=""),"—",IF(E18="Long",(G18-V18)*H18*I18,(V18-G18)*H18*I18)),"—") -> 16400000 | Y18: =IFERROR(IF(OR(V18="",G18=""),"—",IF(E18="Long",(G18-V18)/G18,(V18-G18)/G18)),"—") -> 0.0052449789 | Z18: =IFERROR(IF(OR(W18="",I18=""),"—",IF(E18="Long",(W18-G18)*H18*I18,(G18-W18)*H18*I18)),"—") -> 22800000 | AA18: =IFERROR(IF(OR(W18="",G18=""),"—",IF(E18="Long",(W18-G18)/G18,(G18-W18)/G18)),"—") -> 0.0072917999 | AB18: Bearish outlook on USD appreciation with investors rushing to safe assets | AC18: =IFERROR(IF(E18="Long",(G18-V18)*H18*I18,(V18-G18)*H18*I18),"") -> 16400000 | AD18: =IFERROR(IF(OR(AF18="STOP LOSS HIT",AF18="TAKE PROFIT HIT"),AG18,""),"") -> 0.776 | AE18: =IFERROR(IF(E18="Long",(IF(AND(B18="Closed",AD18<>""),AD18,O18)-G18)/G18,(G18-IF(AND(B18="Closed",AD18<>""),AD18,O18))/G18),"") -> 0.0072917999 | AF18: =IFERROR(IF(OR(V18="",W18=""),"No SL/TP",IF(E18="Long",IF(O18<=V18,"STOP LOSS HIT",IF(O18>=W18,"TAKE PROFIT HIT",IF(B18="Closed","CLOSED","Active"))),IF(O18>=V18,"STOP LOSS HIT",IF(O18<=W18,"TAKE PROFIT HIT",IF(B18="Closed","CLOSED","Active"))))),"—") -> TAKE PROFIT HIT | AG18: =IFERROR(IF(E18="Long",IF(O18<=V18,V18,IF(O18>=W18,W18,"")),IF(O18>=V18,V18,IF(O18<=W18,W18,""))),"") -> 0.776 | AH18: =IFERROR(IF(B18<>"Open","—",IF(E18="Long",G18*(1-1/I18),G18*(1+1/I18))),"—") -> —
A19: =IFERROR(ROW()-5,"") -> 14 | B19: Closed | C19: Stock | D19: AMZN | E19: Long | F19: 46086 | G19: 212.415 | H19: 1500000 | I19: 10 | J19: =IFERROR(1/I19,"") -> 0.1 | K19: =IFERROR(G19*H19*I19,"") -> 3186225000 | L19: =IFERROR(G19*H19,"") -> 318622500 | M19: 0.5 | N19: =IFERROR(IF(B19<>"Open","—",IF((G19*H19+Q19)<=0,"LIQUIDATION",IF((G19*H19+Q19)/(G19*H19)<=M19,"WARNING","OK"))),"—") -> — | O19: 214.5 | P19: =IFERROR((IF(AND(B19="Closed",AD19<>""),AD19,O19))*H19,"") -> 321750000 | Q19: =IFERROR(IF(E19="Long",(IF(AND(B19="Closed",AD19<>""),AD19,O19)-G19)*H19*I19,(G19-IF(AND(B19="Closed",AD19<>""),AD19,O19))*H19*I19),"") -> 31275000 | R19: =IFERROR(Q19/(G19*H19),"") -> 0.09815691 | S19: =IFERROR(L19/(IFERROR(LOOKUP(2,1/('Transaction Log'!H5:H106<>""),'Transaction Log'!H5:H106),0)),"") -> 0.15542561 | T19: 46091 | U19: =IFERROR(IF(B19="Closed",T19-F19,TODAY()-F19),"") -> 5 | V19: 208 | W19: 214.5 | X19: =IFERROR(IF(OR(V19="",I19=""),"—",IF(E19="Long",(G19-V19)*H19*I19,(V19-G19)*H19*I19)),"—") -> 66225000 | Y19: =IFERROR(IF(OR(V19="",G19=""),"—",IF(E19="Long",(G19-V19)/G19,(V19-G19)/G19)),"—") -> 0.020784785 | Z19: =IFERROR(IF(OR(W19="",I19=""),"—",IF(E19="Long",(W19-G19)*H19*I19,(G19-W19)*H19*I19)),"—") -> 31275000 | AA19: =IFERROR(IF(OR(W19="",G19=""),"—",IF(E19="Long",(W19-G19)/G19,(G19-W19)/G19)),"—") -> 0.009815691 | AB19: Market volatility swing trade | AC19: =IFERROR(IF(E19="Long",(G19-V19)*H19*I19,(V19-G19)*H19*I19),"") -> 66225000 | AD19: =IFERROR(IF(OR(AF19="STOP LOSS HIT",AF19="TAKE PROFIT HIT"),AG19,""),"") -> 214.5 | AE19: =IFERROR(IF(E19="Long",(IF(AND(B19="Closed",AD19<>""),AD19,O19)-G19)/G19,(G19-IF(AND(B19="Closed",AD19<>""),AD19,O19))/G19),"") -> 0.009815691 | AF19: =IFERROR(IF(OR(V19="",W19=""),"No SL/TP",IF(E19="Long",IF(O19<=V19,"STOP LOSS HIT",IF(O19>=W19,"TAKE PROFIT HIT",IF(B19="Closed","CLOSED","Active"))),IF(O19>=V19,"STOP LOSS HIT",IF(O19<=W19,"TAKE PROFIT HIT",IF(B19="Closed","CLOSED","Active"))))),"—") -> TAKE PROFIT HIT | AG19: =IFERROR(IF(E19="Long",IF(O19<=V19,V19,IF(O19>=W19,W19,"")),IF(O19>=V19,V19,IF(O19<=W19,W19,""))),"") -> 214.5 | AH19: =IFERROR(IF(B19<>"Open","—",IF(E19="Long",G19*(1-1/I19),G19*(1+1/I19))),"—") -> —
A20: =IFERROR(ROW()-5,"") -> 15 | B20: Closed | C20: Crypto | D20: BTC | E20: Short | F20: 46086 | G20: 72775.14 | H20: 8000 | I20: 10 | J20: =IFERROR(1/I20,"") -> 0.1 | K20: =IFERROR(G20*H20*I20,"") -> 5822011200 | L20: =IFERROR(G20*H20,"") -> 582201120 | M20: 0.5 | N20: =IFERROR(IF(B20<>"Open","—",IF((G20*H20+Q20)<=0,"LIQUIDATION",IF((G20*H20+Q20)/(G20*H20)<=M20,"WARNING","OK"))),"—") -> — | O20: 72150 | P20: =IFERROR((IF(AND(B20="Closed",AD20<>""),AD20,O20))*H20,"") -> 577200000 | Q20: =IFERROR(IF(E20="Long",(IF(AND(B20="Closed",AD20<>""),AD20,O20)-G20)*H20*I20,(G20-IF(AND(B20="Closed",AD20<>""),AD20,O20))*H20*I20),"") -> 50011200 | R20: =IFERROR(Q20/(G20*H20),"") -> 0.085900213 | S20: =IFERROR(L20/(IFERROR(LOOKUP(2,1/('Transaction Log'!H5:H106<>""),'Transaction Log'!H5:H106),0)),"") -> 0.28400055 | T20: 46086 | U20: =IFERROR(IF(B20="Closed",T20-F20,TODAY()-F20),"") -> 0 | V20: 75240 | W20: 72150 | X20: =IFERROR(IF(OR(V20="",I20=""),"—",IF(E20="Long",(G20-V20)*H20*I20,(V20-G20)*H20*I20)),"—") -> 1.971888e+08 | Y20: =IFERROR(IF(OR(V20="",G20=""),"—",IF(E20="Long",(G20-V20)/G20,(V20-G20)/G20)),"—") -> 0.033869533 | Z20: =IFERROR(IF(OR(W20="",I20=""),"—",IF(E20="Long",(W20-G20)*H20*I20,(G20-W20)*H20*I20)),"—") -> 50011200 | AA20: =IFERROR(IF(OR(W20="",G20=""),"—",IF(E20="Long",(W20-G20)/G20,(G20-W20)/G20)),"—") -> 0.0085900213 | AB20: BTC SHORT POSITION HOLD | AC20: =IFERROR(IF(E20="Long",(G20-V20)*H20*I20,(V20-G20)*H20*I20),"") -> 1.971888e+08 | AD20: =IFERROR(IF(OR(AF20="STOP LOSS HIT",AF20="TAKE PROFIT HIT"),AG20,""),"") -> 72150 | AE20: =IFERROR(IF(E20="Long",(IF(AND(B20="Closed",AD20<>""),AD20,O20)-G20)/G20,(G20-IF(AND(B20="Closed",AD20<>""),AD20,O20))/G20),"") -> 0.0085900213 | AF20: =IFERROR(IF(OR(V20="",W20=""),"No SL/TP",IF(E20="Long",IF(O20<=V20,"STOP LOSS HIT",IF(O20>=W20,"TAKE PROFIT HIT",IF(B20="Closed","CLOSED","Active"))),IF(O20>=V20,"STOP LOSS HIT",IF(O20<=W20,"TAKE PROFIT HIT",IF(B20="Closed","CLOSED","Active"))))),"—") -> TAKE PROFIT HIT | AG20: =IFERROR(IF(E20="Long",IF(O20<=V20,V20,IF(O20>=W20,W20,"")),IF(O20>=V20,V20,IF(O20<=W20,W20,""))),"") -> 72150 | AH20: =IFERROR(IF(B20<>"Open","—",IF(E20="Long",G20*(1-1/I20),G20*(1+1/I20))),"—") -> —
A21: =IFERROR(ROW()-5,"") -> 16 | B21: Closed | C21: Stock | D21: NFLX | E21: Short | F21: 46086 | G21: 98.875 | H21: 6000000 | I21: 10 | J21: =IFERROR(1/I21,"") -> 0.1 | K21: =IFERROR(G21*H21*I21,"") -> 5932500000 | L21: =IFERROR(G21*H21,"") -> 593250000 | M21: 0.5 | N21: =IFERROR(IF(B21<>"Open","—",IF((G21*H21+Q21)<=0,"LIQUIDATION",IF((G21*H21+Q21)/(G21*H21)<=M21,"WARNING","OK"))),"—") -> — | O21: 98.1 | P21: =IFERROR((IF(AND(B21="Closed",AD21<>""),AD21,O21))*H21,"") -> 588600000 | Q21: =IFERROR(IF(E21="Long",(IF(AND(B21="Closed",AD21<>""),AD21,O21)-G21)*H21*I21,(G21-IF(AND(B21="Closed",AD21<>""),AD21,O21))*H21*I21),"") -> 46500000 | R21: =IFERROR(Q21/(G21*H21),"") -> 0.078381795 | S21: =IFERROR(L21/(IFERROR(LOOKUP(2,1/('Transaction Log'!H5:H106<>""),'Transaction Log'!H5:H106),0)),"") -> 0.28939024 | T21: 46086 | U21: =IFERROR(IF(B21="Closed",T21-F21,TODAY()-F21),"") -> 0 | V21: 99.43 | W21: 97.85 | X21: =IFERROR(IF(OR(V21="",I21=""),"—",IF(E21="Long",(G21-V21)*H21*I21,(V21-G21)*H21*I21)),"—") -> 33300000 | Y21: =IFERROR(IF(OR(V21="",G21=""),"—",IF(E21="Long",(G21-V21)/G21,(V21-G21)/G21)),"—") -> 0.0056131479 | Z21: =IFERROR(IF(OR(W21="",I21=""),"—",IF(E21="Long",(W21-G21)*H21*I21,(G21-W21)*H21*I21)),"—") -> 61500000 | AA21: =IFERROR(IF(OR(W21="",G21=""),"—",IF(E21="Long",(W21-G21)/G21,(G21-W21)/G21)),"—") -> 0.010366625 | AB21: Netflix Short position Day trade bearish sentiment | AC21: =IFERROR(IF(E21="Long",(G21-V21)*H21*I21,(V21-G21)*H21*I21),"") -> 33300000 | AD21: =IFERROR(IF(OR(AF21="STOP LOSS HIT",AF21="TAKE PROFIT HIT"),AG21,""),"") | AE21: =IFERROR(IF(E21="Long",(IF(AND(B21="Closed",AD21<>""),AD21,O21)-G21)/G21,(G21-IF(AND(B21="Closed",AD21<>""),AD21,O21))/G21),"") -> 0.0078381795 | AF21: =IFERROR(IF(OR(V21="",W21=""),"No SL/TP",IF(E21="Long",IF(O21<=V21,"STOP LOSS HIT",IF(O21>=W21,"TAKE PROFIT HIT",IF(B21="Closed","CLOSED","Active"))),IF(O21>=V21,"STOP LOSS HIT",IF(O21<=W21,"TAKE PROFIT HIT",IF(B21="Closed","CLOSED","Active"))))),"—") -> CLOSED | AG21: =IFERROR(IF(E21="Long",IF(O21<=V21,V21,IF(O21>=W21,W21,"")),IF(O21>=V21,V21,IF(O21<=W21,W21,""))),"") | AH21: =IFERROR(IF(B21<>"Open","—",IF(E21="Long",G21*(1-1/I21),G21*(1+1/I21))),"—") -> —
A22: =IFERROR(ROW()-5,"") -> 17 | B22: Closed | C22: Index | D22: S&P 500 | E22: Short | F22: 46086 | G22: 6869.5 | H22: 25000 | I22: 10 | J22: =IFERROR(1/I22,"") -> 0.1 | K22: =IFERROR(G22*H22*I22,"") -> 1717375000 | L22: =IFERROR(G22*H22,"") -> 171737500 | M22: 0.5 | N22: =IFERROR(IF(B22<>"Open","—",IF((G22*H22+Q22)<=0,"LIQUIDATION",IF((G22*H22+Q22)/(G22*H22)<=M22,"WARNING","OK"))),"—") -> — | O22: 6835 | P22: =IFERROR((IF(AND(B22="Closed",AD22<>""),AD22,O22))*H22,"") -> 170875000 | Q22: =IFERROR(IF(E22="Long",(IF(AND(B22="Closed",AD22<>""),AD22,O22)-G22)*H22*I22,(G22-IF(AND(B22="Closed",AD22<>""),AD22,O22))*H22*I22),"") -> 8625000 | R22: =IFERROR(Q22/(G22*H22),"") -> 0.050221996 | S22: =IFERROR(L22/(IFERROR(LOOKUP(2,1/('Transaction Log'!H5:H106<>""),'Transaction Log'!H5:H106),0)),"") -> 0.08377439 | T22: 46086 | U22: =IFERROR(IF(B22="Closed",T22-F22,TODAY()-F22),"") -> 0 | V22: 6969 | W22: 6835 | X22: =IFERROR(IF(OR(V22="",I22=""),"—",IF(E22="Long",(G22-V22)*H22*I22,(V22-G22)*H22*I22)),"—") -> 24875000 | Y22: =IFERROR(IF(OR(V22="",G22=""),"—",IF(E22="Long",(G22-V22)/G22,(V22-G22)/G22)),"—") -> 0.014484315 | Z22: =IFERROR(IF(OR(W22="",I22=""),"—",IF(E22="Long",(W22-G22)*H22*I22,(G22-W22)*H22*I22)),"—") -> 8625000 | AA22: =IFERROR(IF(OR(W22="",G22=""),"—",IF(E22="Long",(W22-G22)/G22,(G22-W22)/G22)),"—") -> 0.0050221996 | AB22: Market Opening Swing | AC22: =IFERROR(IF(E22="Long",(G22-V22)*H22*I22,(V22-G22)*H22*I22),"") -> 24875000 | AD22: =IFERROR(IF(OR(AF22="STOP LOSS HIT",AF22="TAKE PROFIT HIT"),AG22,""),"") -> 6835 | AE22: =IFERROR(IF(E22="Long",(IF(AND(B22="Closed",AD22<>""),AD22,O22)-G22)/G22,(G22-IF(AND(B22="Closed",AD22<>""),AD22,O22))/G22),"") -> 0.0050221996 | AF22: =IFERROR(IF(OR(V22="",W22=""),"No SL/TP",IF(E22="Long",IF(O22<=V22,"STOP LOSS HIT",IF(O22>=W22,"TAKE PROFIT HIT",IF(B22="Closed","CLOSED","Active"))),IF(O22>=V22,"STOP LOSS HIT",IF(O22<=W22,"TAKE PROFIT HIT",IF(B22="Closed","CLOSED","Active"))))),"—") -> TAKE PROFIT HIT | AG22: =IFERROR(IF(E22="Long",IF(O22<=V22,V22,IF(O22>=W22,W22,"")),IF(O22>=V22,V22,IF(O22<=W22,W22,""))),"") -> 6835 | AH22: =IFERROR(IF(B22<>"Open","—",IF(E22="Long",G22*(1-1/I22),G22*(1+1/I22))),"—") -> —
A23: =IFERROR(ROW()-5,"") -> 18 | B23: Closed | C23: Futures | D23: Oil | E23: Long | F23: 46086 | G23: 78.78 | H23: 750000 | I23: 20 | J23: =IFERROR(1/I23,"") -> 0.05 | K23: =IFERROR(G23*H23*I23,"") -> 1181700000 | L23: =IFERROR(G23*H23,"") -> 59085000 | M23: 0.5 | N23: =IFERROR(IF(B23<>"Open","—",IF((G23*H23+Q23)<=0,"LIQUIDATION",IF((G23*H23+Q23)/(G23*H23)<=M23,"WARNING","OK"))),"—") -> — | O23: 79.2 | P23: =IFERROR((IF(AND(B23="Closed",AD23<>""),AD23,O23))*H23,"") -> 59400000 | Q23: =IFERROR(IF(E23="Long",(IF(AND(B23="Closed",AD23<>""),AD23,O23)-G23)*H23*I23,(G23-IF(AND(B23="Closed",AD23<>""),AD23,O23))*H23*I23),"") -> 6300000 | R23: =IFERROR(Q23/(G23*H23),"") -> 0.10662605 | S23: =IFERROR(L23/(IFERROR(LOOKUP(2,1/('Transaction Log'!H5:H106<>""),'Transaction Log'!H5:H106),0)),"") -> 0.028821951 | T23: 46086 | U23: =IFERROR(IF(B23="Closed",T23-F23,TODAY()-F23),"") -> 0 | V23: 77.9 | W23: 79.2 | X23: =IFERROR(IF(OR(V23="",I23=""),"—",IF(E23="Long",(G23-V23)*H23*I23,(V23-G23)*H23*I23)),"—") -> 13200000 | Y23: =IFERROR(IF(OR(V23="",G23=""),"—",IF(E23="Long",(G23-V23)/G23,(V23-G23)/G23)),"—") -> 0.011170348 | Z23: =IFERROR(IF(OR(W23="",I23=""),"—",IF(E23="Long",(W23-G23)*H23*I23,(G23-W23)*H23*I23)),"—") -> 6300000 | AA23: =IFERROR(IF(OR(W23="",G23=""),"—",IF(E23="Long",(W23-G23)/G23,(G23-W23)/G23)),"—") -> 0.0053313024 | AB23: US Oil price jumps pullback swing | AC23: =IFERROR(IF(E23="Long",(G23-V23)*H23*I23,(V23-G23)*H23*I23),"") -> 13200000 | AD23: =IFERROR(IF(OR(AF23="STOP LOSS HIT",AF23="TAKE PROFIT HIT"),AG23,""),"") -> 79.2 | AE23: =IFERROR(IF(E23="Long",(IF(AND(B23="Closed",AD23<>""),AD23,O23)-G23)/G23,(G23-IF(AND(B23="Closed",AD23<>""),AD23,O23))/G23),"") -> 0.0053313024 | AF23: =IFERROR(IF(OR(V23="",W23=""),"No SL/TP",IF(E23="Long",IF(O23<=V23,"STOP LOSS HIT",IF(O23>=W23,"TAKE PROFIT HIT",IF(B23="Closed","CLOSED","Active"))),IF(O23>=V23,"STOP LOSS HIT",IF(O23<=W23,"TAKE PROFIT HIT",IF(B23="Closed","CLOSED","Active"))))),"—") -> TAKE PROFIT HIT | AG23: =IFERROR(IF(E23="Long",IF(O23<=V23,V23,IF(O23>=W23,W23,"")),IF(O23>=V23,V23,IF(O23<=W23,W23,""))),"") -> 79.2 | AH23: =IFERROR(IF(B23<>"Open","—",IF(E23="Long",G23*(1-1/I23),G23*(1+1/I23))),"—") -> —
A24: =IFERROR(ROW()-5,"") -> 19 | B24: Closed | C24: Forex | D24: USD/JPY | E24: Short | F24: 46085 | G24: 157 | H24: 800000 | I24: 20 | J24: =IFERROR(1/I24,"") -> 0.05 | K24: =IFERROR(G24*H24*I24,"") -> 2512000000 | L24: =IFERROR(G24*H24,"") -> 125600000 | M24: 0.5 | N24: =IFERROR(IF(B24<>"Open","—",IF((G24*H24+Q24)<=0,"LIQUIDATION",IF((G24*H24+Q24)/(G24*H24)<=M24,"WARNING","OK"))),"—") -> — | O24: 156.72 | P24: =IFERROR((IF(AND(B24="Closed",AD24<>""),AD24,O24))*H24,"") -> 125376000 | Q24: =IFERROR(IF(E24="Long",(IF(AND(B24="Closed",AD24<>""),AD24,O24)-G24)*H24*I24,(G24-IF(AND(B24="Closed",AD24<>""),AD24,O24))*H24*I24),"") -> 4480000 | R24: =IFERROR(Q24/(G24*H24),"") -> 0.03566879 | S24: =IFERROR(L24/(IFERROR(LOOKUP(2,1/('Transaction Log'!H5:H106<>""),'Transaction Log'!H5:H106),0)),"") -> 0.061268293 | T24: 46086 | U24: =IFERROR(IF(B24="Closed",T24-F24,TODAY()-F24),"") -> 1 | V24: 158.7 | W24: 156.72 | X24: =IFERROR(IF(OR(V24="",I24=""),"—",IF(E24="Long",(G24-V24)*H24*I24,(V24-G24)*H24*I24)),"—") -> 27200000 | Y24: =IFERROR(IF(OR(V24="",G24=""),"—",IF(E24="Long",(G24-V24)/G24,(V24-G24)/G24)),"—") -> 0.010828025 | Z24: =IFERROR(IF(OR(W24="",I24=""),"—",IF(E24="Long",(W24-G24)*H24*I24,(G24-W24)*H24*I24)),"—") -> 4480000 | AA24: =IFERROR(IF(OR(W24="",G24=""),"—",IF(E24="Long",(W24-G24)/G24,(G24-W24)/G24)),"—") -> 0.0017834395 | AB24: USD depreciation for tension, Market sentiment bearish | AC24: =IFERROR(IF(E24="Long",(G24-V24)*H24*I24,(V24-G24)*H24*I24),"") -> 27200000 | AD24: =IFERROR(IF(OR(AF24="STOP LOSS HIT",AF24="TAKE PROFIT HIT"),AG24,""),"") -> 156.72 | AE24: =IFERROR(IF(E24="Long",(IF(AND(B24="Closed",AD24<>""),AD24,O24)-G24)/G24,(G24-IF(AND(B24="Closed",AD24<>""),AD24,O24))/G24),"") -> 0.0017834395 | AF24: =IFERROR(IF(OR(V24="",W24=""),"No SL/TP",IF(E24="Long",IF(O24<=V24,"STOP LOSS HIT",IF(O24>=W24,"TAKE PROFIT HIT",IF(B24="Closed","CLOSED","Active"))),IF(O24>=V24,"STOP LOSS HIT",IF(O24<=W24,"TAKE PROFIT HIT",IF(B24="Closed","CLOSED","Active"))))),"—") -> TAKE PROFIT HIT | AG24: =IFERROR(IF(E24="Long",IF(O24<=V24,V24,IF(O24>=W24,W24,"")),IF(O24>=V24,V24,IF(O24<=W24,W24,""))),"") -> 156.72 | AH24: =IFERROR(IF(B24<>"Open","—",IF(E24="Long",G24*(1-1/I24),G24*(1+1/I24))),"—") -> —
A25: =IFERROR(ROW()-5,"") -> 20 | B25: Closed | C25: Crypto | D25: BTC | E25: Short | F25: 46085 | G25: 73988 | H25: 1000 | I25: 5 | J25: =IFERROR(1/I25,"") -> 0.2 | K25: =IFERROR(G25*H25*I25,"") -> 369940000 | L25: =IFERROR(G25*H25,"") -> 73988000 | M25: 0.5 | N25: =IFERROR(IF(B25<>"Open","—",IF((G25*H25+Q25)<=0,"LIQUIDATION",IF((G25*H25+Q25)/(G25*H25)<=M25,"WARNING","OK"))),"—") -> — | O25: 73370.54 | P25: =IFERROR((IF(AND(B25="Closed",AD25<>""),AD25,O25))*H25,"") -> 73370540 | Q25: =IFERROR(IF(E25="Long",(IF(AND(B25="Closed",AD25<>""),AD25,O25)-G25)*H25*I25,(G25-IF(AND(B25="Closed",AD25<>""),AD25,O25))*H25*I25),"") -> 3087300 | R25: =IFERROR(Q25/(G25*H25),"") -> 0.041727037 | S25: =IFERROR(L25/(IFERROR(LOOKUP(2,1/('Transaction Log'!H5:H106<>""),'Transaction Log'!H5:H106),0)),"") -> 0.036091707 | T25: 46085 | U25: =IFERROR(IF(B25="Closed",T25-F25,TODAY()-F25),"") -> 0 | V25: 74250 | W25: 72560 | X25: =IFERROR(IF(OR(V25="",I25=""),"—",IF(E25="Long",(G25-V25)*H25*I25,(V25-G25)*H25*I25)),"—") -> 1310000 | Y25: =IFERROR(IF(OR(V25="",G25=""),"—",IF(E25="Long",(G25-V25)/G25,(V25-G25)/G25)),"—") -> 0.0035411148 | Z25: =IFERROR(IF(OR(W25="",I25=""),"—",IF(E25="Long",(W25-G25)*H25*I25,(G25-W25)*H25*I25)),"—") -> 7140000 | AA25: =IFERROR(IF(OR(W25="",G25=""),"—",IF(E25="Long",(W25-G25)/G25,(G25-W25)/G25)),"—") -> 0.019300427 | AB25: Geopolitical tensions short-term | AC25: =IFERROR(IF(E25="Long",(G25-V25)*H25*I25,(V25-G25)*H25*I25),"") -> 1310000 | AD25: =IFERROR(IF(OR(AF25="STOP LOSS HIT",AF25="TAKE PROFIT HIT"),AG25,""),"") | AE25: =IFERROR(IF(E25="Long",(IF(AND(B25="Closed",AD25<>""),AD25,O25)-G25)/G25,(G25-IF(AND(B25="Closed",AD25<>""),AD25,O25))/G25),"") -> 0.0083454074 | AF25: =IFERROR(IF(OR(V25="",W25=""),"No SL/TP",IF(E25="Long",IF(O25<=V25,"STOP LOSS HIT",IF(O25>=W25,"TAKE PROFIT HIT",IF(B25="Closed","CLOSED","Active"))),IF(O25>=V25,"STOP LOSS HIT",IF(O25<=W25,"TAKE PROFIT HIT",IF(B25="Closed","CLOSED","Active"))))),"—") -> CLOSED | AG25: =IFERROR(IF(E25="Long",IF(O25<=V25,V25,IF(O25>=W25,W25,"")),IF(O25>=V25,V25,IF(O25<=W25,W25,""))),"") | AH25: =IFERROR(IF(B25<>"Open","—",IF(E25="Long",G25*(1-1/I25),G25*(1+1/I25))),"—") -> —
A26: =IFERROR(ROW()-5,"") -> 21 | B26: Closed | C26: Stock | D26: RHMD | E26: Short | F26: 46085 | G26: 1599.5 | H26: 5000 | I26: 10 | J26: =IFERROR(1/I26,"") -> 0.1 | K26: =IFERROR(G26*H26*I26,"") -> 79975000 | L26: =IFERROR(G26*H26,"") -> 7997500 | M26: 0.5 | N26: =IFERROR(IF(B26<>"Open","—",IF((G26*H26+Q26)<=0,"LIQUIDATION",IF((G26*H26+Q26)/(G26*H26)<=M26,"WARNING","OK"))),"—") -> — | O26: 1570 | P26: =IFERROR((IF(AND(B26="Closed",AD26<>""),AD26,O26))*H26,"") -> 7850000 | Q26: =IFERROR(IF(E26="Long",(IF(AND(B26="Closed",AD26<>""),AD26,O26)-G26)*H26*I26,(G26-IF(AND(B26="Closed",AD26<>""),AD26,O26))*H26*I26),"") -> 1475000 | R26: =IFERROR(Q26/(G26*H26),"") -> 0.18443264 | S26: =IFERROR(L26/(IFERROR(LOOKUP(2,1/('Transaction Log'!H5:H106<>""),'Transaction Log'!H5:H106),0)),"") -> 0.0039012195 | T26: 46086 | U26: =IFERROR(IF(B26="Closed",T26-F26,TODAY()-F26),"") -> 1 | V26: 1620 | W26: 1570 | X26: =IFERROR(IF(OR(V26="",I26=""),"—",IF(E26="Long",(G26-V26)*H26*I26,(V26-G26)*H26*I26)),"—") -> 1025000 | Y26: =IFERROR(IF(OR(V26="",G26=""),"—",IF(E26="Long",(G26-V26)/G26,(V26-G26)/G26)),"—") -> 0.012816505 | Z26: =IFERROR(IF(OR(W26="",I26=""),"—",IF(E26="Long",(W26-G26)*H26*I26,(G26-W26)*H26*I26)),"—") -> 1475000 | AA26: =IFERROR(IF(OR(W26="",G26=""),"—",IF(E26="Long",(W26-G26)/G26,(G26-W26)/G26)),"—") -> 0.018443264 | AB26: European defense budget increase but looks bearish | AC26: =IFERROR(IF(E26="Long",(G26-V26)*H26*I26,(V26-G26)*H26*I26),"") -> 1025000 | AD26: =IFERROR(IF(OR(AF26="STOP LOSS HIT",AF26="TAKE PROFIT HIT"),AG26,""),"") -> 1570 | AE26: =IFERROR(IF(E26="Long",(IF(AND(B26="Closed",AD26<>""),AD26,O26)-G26)/G26,(G26-IF(AND(B26="Closed",AD26<>""),AD26,O26))/G26),"") -> 0.018443264 | AF26: =IFERROR(IF(OR(V26="",W26=""),"No SL/TP",IF(E26="Long",IF(O26<=V26,"STOP LOSS HIT",IF(O26>=W26,"TAKE PROFIT HIT",IF(B26="Closed","CLOSED","Active"))),IF(O26>=V26,"STOP LOSS HIT",IF(O26<=W26,"TAKE PROFIT HIT",IF(B26="Closed","CLOSED","Active"))))),"—") -> TAKE PROFIT HIT | AG26: =IFERROR(IF(E26="Long",IF(O26<=V26,V26,IF(O26>=W26,W26,"")),IF(O26>=V26,V26,IF(O26<=W26,W26,""))),"") -> 1570 | AH26: =IFERROR(IF(B26<>"Open","—",IF(E26="Long",G26*(1-1/I26),G26*(1+1/I26))),"—") -> —
A27: =IFERROR(ROW()-5,"") -> 22 | B27: Closed | C27: ETF | D27: REMX | E27: Long | F27: 46085 | G27: 20.69 | H27: 800000 | I27: 25 | J27: =IFERROR(1/I27,"") -> 0.04 | K27: =IFERROR(G27*H27*I27,"") -> 4.138e+08 | L27: =IFERROR(G27*H27,"") -> 16552000 | M27: 0.5 | N27: =IFERROR(IF(B27<>"Open","—",IF((G27*H27+Q27)<=0,"LIQUIDATION",IF((G27*H27+Q27)/(G27*H27)<=M27,"WARNING","OK"))),"—") -> — | O27: 20.47 | P27: =IFERROR((IF(AND(B27="Closed",AD27<>""),AD27,O27))*H27,"") -> 16376000 | Q27: =IFERROR(IF(E27="Long",(IF(AND(B27="Closed",AD27<>""),AD27,O27)-G27)*H27*I27,(G27-IF(AND(B27="Closed",AD27<>""),AD27,O27))*H27*I27),"") -> -4400000 | R27: =IFERROR(Q27/(G27*H27),"") -> -0.2658289 | S27: =IFERROR(L27/(IFERROR(LOOKUP(2,1/('Transaction Log'!H5:H106<>""),'Transaction Log'!H5:H106),0)),"") -> 0.0080741463 | T27: 46086 | U27: =IFERROR(IF(B27="Closed",T27-F27,TODAY()-F27),"") -> 1 | V27: 20.47 | W27: 21.3 | X27: =IFERROR(IF(OR(V27="",I27=""),"—",IF(E27="Long",(G27-V27)*H27*I27,(V27-G27)*H27*I27)),"—") -> 4400000 | Y27: =IFERROR(IF(OR(V27="",G27=""),"—",IF(E27="Long",(G27-V27)/G27,(V27-G27)/G27)),"—") -> 0.010633156 | Z27: =IFERROR(IF(OR(W27="",I27=""),"—",IF(E27="Long",(W27-G27)*H27*I27,(G27-W27)*H27*I27)),"—") -> 12200000 | AA27: =IFERROR(IF(OR(W27="",G27=""),"—",IF(E27="Long",(W27-G27)/G27,(G27-W27)/G27)),"—") -> 0.029482842 | AB27: Rare minerals demand increase + tech ind. need | AC27: =IFERROR(IF(E27="Long",(G27-V27)*H27*I27,(V27-G27)*H27*I27),"") -> 4400000 | AD27: =IFERROR(IF(OR(AF27="STOP LOSS HIT",AF27="TAKE PROFIT HIT"),AG27,""),"") -> 20.47 | AE27: =IFERROR(IF(E27="Long",(IF(AND(B27="Closed",AD27<>""),AD27,O27)-G27)/G27,(G27-IF(AND(B27="Closed",AD27<>""),AD27,O27))/G27),"") -> -0.010633156 | AF27: =IFERROR(IF(OR(V27="",W27=""),"No SL/TP",IF(E27="Long",IF(O27<=V27,"STOP LOSS HIT",IF(O27>=W27,"TAKE PROFIT HIT",IF(B27="Closed","CLOSED","Active"))),IF(O27>=V27,"STOP LOSS HIT",IF(O27<=W27,"TAKE PROFIT HIT",IF(B27="Closed","CLOSED","Active"))))),"—") -> STOP LOSS HIT | AG27: =IFERROR(IF(E27="Long",IF(O27<=V27,V27,IF(O27>=W27,W27,"")),IF(O27>=V27,V27,IF(O27<=W27,W27,""))),"") -> 20.47 | AH27: =IFERROR(IF(B27<>"Open","—",IF(E27="Long",G27*(1-1/I27),G27*(1+1/I27))),"—") -> —
A28: =IFERROR(ROW()-5,"") -> 23 | B28: Closed | C28: Futures | D28: Oil | E28: Long | F28: 46082 | G28: 70.9 | H28: 100000 | I28: 10 | J28: =IFERROR(1/I28,"") -> 0.1 | K28: =IFERROR(G28*H28*I28,"") -> 70900000 | L28: =IFERROR(G28*H28,"") -> 7090000 | M28: 0.5 | N28: =IFERROR(IF(B28<>"Open","—",IF((G28*H28+Q28)<=0,"LIQUIDATION",IF((G28*H28+Q28)/(G28*H28)<=M28,"WARNING","OK"))),"—") -> — | O28: 76 | P28: =IFERROR((IF(AND(B28="Closed",AD28<>""),AD28,O28))*H28,"") -> 7600000 | Q28: =IFERROR(IF(E28="Long",(IF(AND(B28="Closed",AD28<>""),AD28,O28)-G28)*H28*I28,(G28-IF(AND(B28="Closed",AD28<>""),AD28,O28))*H28*I28),"") -> 5100000 | R28: =IFERROR(Q28/(G28*H28),"") -> 0.71932299 | S28: =IFERROR(L28/(IFERROR(LOOKUP(2,1/('Transaction Log'!H5:H106<>""),'Transaction Log'!H5:H106),0)),"") -> 0.0034585366 | T28: 46085 | U28: =IFERROR(IF(B28="Closed",T28-F28,TODAY()-F28),"") -> 3 | V28: 68.5 | W28: 76 | X28: =IFERROR(IF(OR(V28="",I28=""),"—",IF(E28="Long",(G28-V28)*H28*I28,(V28-G28)*H28*I28)),"—") -> 2400000 | Y28: =IFERROR(IF(OR(V28="",G28=""),"—",IF(E28="Long",(G28-V28)/G28,(V28-G28)/G28)),"—") -> 0.033850494 | Z28: =IFERROR(IF(OR(W28="",I28=""),"—",IF(E28="Long",(W28-G28)*H28*I28,(G28-W28)*H28*I28)),"—") -> 5100000 | AA28: =IFERROR(IF(OR(W28="",G28=""),"—",IF(E28="Long",(W28-G28)/G28,(G28-W28)/G28)),"—") -> 0.071932299 | AB28: US-Iran Tensions | AC28: =IFERROR(IF(E28="Long",(G28-V28)*H28*I28,(V28-G28)*H28*I28),"") -> 2400000 | AD28: =IFERROR(IF(OR(AF28="STOP LOSS HIT",AF28="TAKE PROFIT HIT"),AG28,""),"") -> 76 | AE28: =IFERROR(IF(E28="Long",(IF(AND(B28="Closed",AD28<>""),AD28,O28)-G28)/G28,(G28-IF(AND(B28="Closed",AD28<>""),AD28,O28))/G28),"") -> 0.071932299 | AF28: =IFERROR(IF(OR(V28="",W28=""),"No SL/TP",IF(E28="Long",IF(O28<=V28,"STOP LOSS HIT",IF(O28>=W28,"TAKE PROFIT HIT",IF(B28="Closed","CLOSED","Active"))),IF(O28>=V28,"STOP LOSS HIT",IF(O28<=W28,"TAKE PROFIT HIT",IF(B28="Closed","CLOSED","Active"))))),"—") -> TAKE PROFIT HIT | AG28: =IFERROR(IF(E28="Long",IF(O28<=V28,V28,IF(O28>=W28,W28,"")),IF(O28>=V28,V28,IF(O28<=W28,W28,""))),"") -> 76 | AH28: =IFERROR(IF(B28<>"Open","—",IF(E28="Long",G28*(1-1/I28),G28*(1+1/I28))),"—") -> —
A29: =IFERROR(ROW()-5,"") -> 24 | B29: Open | C29: Futures | D29: Oil | E29: Long | F29: 46095 | G29: 97.633 | H29: 1200000 | I29: 20 | J29: =IFERROR(1/I29,"") -> 0.05 | K29: =IFERROR(G29*H29*I29,"") -> 2343192000 | L29: =IFERROR(G29*H29,"") -> 117159600 | M29: 0.5 | N29: =IFERROR(IF(B29<>"Open","—",IF((G29*H29+Q29)<=0,"LIQUIDATION",IF((G29*H29+Q29)/(G29*H29)<=M29,"WARNING","OK"))),"—") -> OK | O29: 98.71 | P29: =IFERROR((IF(AND(B29="Closed",AD29<>""),AD29,O29))*H29,"") -> 1.18452e+08 | Q29: =IFERROR(IF(E29="Long",(IF(AND(B29="Closed",AD29<>""),AD29,O29)-G29)*H29*I29,(G29-IF(AND(B29="Closed",AD29<>""),AD29,O29))*H29*I29),"") -> 25848000 | R29: =IFERROR(Q29/(G29*H29),"") -> 0.22062213 | S29: =IFERROR(L29/(IFERROR(LOOKUP(2,1/('Transaction Log'!H5:H106<>""),'Transaction Log'!H5:H106),0)),"") -> 0.057151024 | U29: =IFERROR(IF(B29="Closed",T29-F29,TODAY()-F29),"") -> 1 | V29: 92 | W29: 148.5 | X29: =IFERROR(IF(OR(V29="",I29=""),"—",IF(E29="Long",(G29-V29)*H29*I29,(V29-G29)*H29*I29)),"—") -> 1.35192e+08 | Y29: =IFERROR(IF(OR(V29="",G29=""),"—",IF(E29="Long",(G29-V29)/G29,(V29-G29)/G29)),"—") -> 0.057695656 | Z29: =IFERROR(IF(OR(W29="",I29=""),"—",IF(E29="Long",(W29-G29)*H29*I29,(G29-W29)*H29*I29)),"—") -> 1.220808e+09 | AA29: =IFERROR(IF(OR(W29="",G29=""),"—",IF(E29="Long",(W29-G29)/G29,(G29-W29)/G29)),"—") -> 0.52100212 | AB29: LONG oil war | AC29: =IFERROR(IF(E29="Long",(G29-V29)*H29*I29,(V29-G29)*H29*I29),"") -> 1.35192e+08 | AD29: =IFERROR(IF(OR(AF29="STOP LOSS HIT",AF29="TAKE PROFIT HIT"),AG29,""),"") | AE29: =IFERROR(IF(E29="Long",(IF(AND(B29="Closed",AD29<>""),AD29,O29)-G29)/G29,(G29-IF(AND(B29="Closed",AD29<>""),AD29,O29))/G29),"") -> 0.011031106 | AF29: =IFERROR(IF(OR(V29="",W29=""),"No SL/TP",IF(E29="Long",IF(O29<=V29,"STOP LOSS HIT",IF(O29>=W29,"TAKE PROFIT HIT",IF(B29="Closed","CLOSED","Active"))),IF(O29>=V29,"STOP LOSS HIT",IF(O29<=W29,"TAKE PROFIT HIT",IF(B29="Closed","CLOSED","Active"))))),"—") -> Active | AG29: =IFERROR(IF(E29="Long",IF(O29<=V29,V29,IF(O29>=W29,W29,"")),IF(O29>=V29,V29,IF(O29<=W29,W29,""))),"") | AH29: =IFERROR(IF(B29<>"Open","—",IF(E29="Long",G29*(1-1/I29),G29*(1+1/I29))),"—") -> 92.75135
A30: =IFERROR(ROW()-5,"") -> 25 | B30: Open | C30: Futures | D30: Oil | E30: Long | F30: 46095 | G30: 97.633 | H30: 800000 | I30: 20 | J30: =IFERROR(1/I30,"") -> 0.05 | K30: =IFERROR(G30*H30*I30,"") -> 1562128000 | L30: =IFERROR(G30*H30,"") -> 78106400 | M30: 0.5 | N30: =IFERROR(IF(B30<>"Open","—",IF((G30*H30+Q30)<=0,"LIQUIDATION",IF((G30*H30+Q30)/(G30*H30)<=M30,"WARNING","OK"))),"—") -> OK | O30: 98.71 | P30: =IFERROR((IF(AND(B30="Closed",AD30<>""),AD30,O30))*H30,"") -> 78968000 | Q30: =IFERROR(IF(E30="Long",(IF(AND(B30="Closed",AD30<>""),AD30,O30)-G30)*H30*I30,(G30-IF(AND(B30="Closed",AD30<>""),AD30,O30))*H30*I30),"") -> 17232000 | R30: =IFERROR(Q30/(G30*H30),"") -> 0.22062213 | S30: =IFERROR(L30/(IFERROR(LOOKUP(2,1/('Transaction Log'!H5:H106<>""),'Transaction Log'!H5:H106),0)),"") -> 0.038100683 | U30: =IFERROR(IF(B30="Closed",T30-F30,TODAY()-F30),"") -> 1 | V30: 92 | W30: 138 | X30: =IFERROR(IF(OR(V30="",I30=""),"—",IF(E30="Long",(G30-V30)*H30*I30,(V30-G30)*H30*I30)),"—") -> 90128000 | Y30: =IFERROR(IF(OR(V30="",G30=""),"—",IF(E30="Long",(G30-V30)/G30,(V30-G30)/G30)),"—") -> 0.057695656 | Z30: =IFERROR(IF(OR(W30="",I30=""),"—",IF(E30="Long",(W30-G30)*H30*I30,(G30-W30)*H30*I30)),"—") -> 6.45872e+08 | AA30: =IFERROR(IF(OR(W30="",G30=""),"—",IF(E30="Long",(W30-G30)/G30,(G30-W30)/G30)),"—") -> 0.41345652 | AB30: LONG Oil war Mult positions | AC30: =IFERROR(IF(E30="Long",(G30-V30)*H30*I30,(V30-G30)*H30*I30),"") -> 90128000 | AD30: =IFERROR(IF(OR(AF30="STOP LOSS HIT",AF30="TAKE PROFIT HIT"),AG30,""),"") | AE30: =IFERROR(IF(E30="Long",(IF(AND(B30="Closed",AD30<>""),AD30,O30)-G30)/G30,(G30-IF(AND(B30="Closed",AD30<>""),AD30,O30))/G30),"") -> 0.011031106 | AF30: =IFERROR(IF(OR(V30="",W30=""),"No SL/TP",IF(E30="Long",IF(O30<=V30,"STOP LOSS HIT",IF(O30>=W30,"TAKE PROFIT HIT",IF(B30="Closed","CLOSED","Active"))),IF(O30>=V30,"STOP LOSS HIT",IF(O30<=W30,"TAKE PROFIT HIT",IF(B30="Closed","CLOSED","Active"))))),"—") -> Active | AG30: =IFERROR(IF(E30="Long",IF(O30<=V30,V30,IF(O30>=W30,W30,"")),IF(O30>=V30,V30,IF(O30<=W30,W30,""))),"") | AH30: =IFERROR(IF(B30<>"Open","—",IF(E30="Long",G30*(1-1/I30),G30*(1+1/I30))),"—") -> 92.75135

Sheet Investor Withdrawals
A1: INVESTOR WITHDRAWALS // LIVE PRO-RATA TRACKER
A2: Net Balance and Fund % auto-recalculate for all players on every deposit or withdrawal.
A3: Blue=input | White=formula | Green=cross-sheet | Partial: enter amt in col O, P&L scales to fraction
A5: # | B5: Player Name | C5: First Deposit Date | D5: Lockup (days) | E5: Unlock Date | F5: Days to Unlock | G5: Lockup Status | H5: Total Deposited ($) | I5: Total Paid Out ($) | J5: Net Balance in Fund ($) | K5: Fund % (live) | L5: Fund P&L ($) | M5: Full P&L Share ($) | N5: Withdrawal Date | O5: Withdrawal Amt ($) | P5: % of Stake Withdrawn | Q5: P&L on Withdrawal ($) | R5: Net Payout ($) | S5: Remaining Balance ($) | T5: New Fund % | U5: Status | V5: Notes
A6: 1 | B6: Kimmo | C6: 46082 | D6: 0 | E6: =IFERROR(C6+D6,"") -> 46082 | F6: =IFERROR(E6-TODAY(),"") -> -14 | G6: =IFERROR(IF(TODAY()>=E6,"UNLOCKED","LOCKED"),"") -> UNLOCKED | H6: =IFERROR(SUMIF('Transaction Log'!C5:C106,B6,'Transaction Log'!E5:E106),0) -> 2000000000 | I6: =IFERROR(SUMIF('Transaction Log'!C5:C106,B6,'Transaction Log'!F5:F106),0) -> 0 | J6: =IFERROR(H6-I6,0) -> 2000000000 | K6: =IFERROR(J6/(IFERROR(LOOKUP(2,1/('Transaction Log'!H5:H106<>""),'Transaction Log'!H5:H106),0)),0) -> 0.97560976 | L6: =IFERROR(SUM(Positions!Q6:Q105),0) -> 1.1832186e+09 | M6: =IFERROR(K6*L6,0) -> 1.1543596e+09 | P6: =IFERROR(O6/J6,0) -> 0 | Q6: =IFERROR(P6*M6,0) -> 0 | R6: =IFERROR(IF(O6>0,O6+Q6,""),"") | S6: =IFERROR(J6-O6,J6) -> 2000000000 | T6: =IFERROR(S6/(IFERROR(LOOKUP(2,1/('Transaction Log'!H5:H106<>""),'Transaction Log'!H5:H106),0)),0) -> 0.97560976 | U6: =IFERROR(IF(J6<=0,"No Balance",IF(O6<=0,"No Withdrawal",IF(TODAY()<E6,"LOCKED",IF(O6>J6,"Exceeds Balance","Approved")))),"—") -> No Withdrawal
A7: 2 | B7: Andre | C7: 46093 | D7: 30 | E7: =IFERROR(C7+D7,"") -> 46123 | F7: =IFERROR(E7-TODAY(),"") -> 27 | G7: =IFERROR(IF(TODAY()>=E7,"UNLOCKED","LOCKED"),"") -> LOCKED | H7: =IFERROR(SUMIF('Transaction Log'!C5:C106,B7,'Transaction Log'!E5:E106),0) -> 50000000 | I7: =IFERROR(SUMIF('Transaction Log'!C5:C106,B7,'Transaction Log'!F5:F106),0) -> 0 | J7: =IFERROR(H7-I7,0) -> 50000000 | K7: =IFERROR(J7/(IFERROR(LOOKUP(2,1/('Transaction Log'!H5:H106<>""),'Transaction Log'!H5:H106),0)),0) -> 0.024390244 | L7: =IFERROR(SUM(Positions!Q6:Q105),0) -> 1.1832186e+09 | M7: =IFERROR(K7*L7,0) -> 28858989 | N7: =C7+30 -> 46123 | O7: 50000000 | P7: =IFERROR(O7/J7,0) -> 1 | Q7: =IFERROR(P7*M7,0) -> 28858989 | R7: =IFERROR(IF(O7>0,O7+Q7,""),"") -> 78858989 | S7: =IFERROR(J7-O7,J7) -> 0 | T7: =IFERROR(S7/(IFERROR(LOOKUP(2,1/('Transaction Log'!H5:H106<>""),'Transaction Log'!H5:H106),0)),0) -> 0 | U7: =IFERROR(IF(J7<=0,"No Balance",IF(O7<=0,"No Withdrawal",IF(TODAY()<E7,"LOCKED",IF(O7>J7,"Exceeds Balance","Approved")))),"—") -> LOCKED | V7: Redistribution upon unlock
A8: 3 | E8: =IFERROR(C8+D8,"") -> 0 | F8: =IFERROR(E8-TODAY(),"") -> -46096 | G8: =IFERROR(IF(TODAY()>=E8,"UNLOCKED","LOCKED"),"") -> UNLOCKED | H8: =IFERROR(SUMIF('Transaction Log'!C5:C106,B8,'Transaction Log'!E5:E106),0) -> 0 | I8: =IFERROR(SUMIF('Transaction Log'!C5:C106,B8,'Transaction Log'!F5:F106),0) -> 0 | J8: =IFERROR(H8-I8,0) -> 0 | K8: =IFERROR(J8/(IFERROR(LOOKUP(2,1/('Transaction Log'!H5:H106<>""),'Transaction Log'!H5:H106),0)),0) -> 0 | L8: =IFERROR(SUM(Positions!Q6:Q105),0) -> 1.1832186e+09 | M8: =IFERROR(K8*L8,0) -> 0 | P8: =IFERROR(O8/J8,0) -> 0 | Q8: =IFERROR(P8*M8,0) -> 0 | R8: =IFERROR(IF(O8>0,O8+Q8,""),"") | S8: =IFERROR(J8-O8,J8) -> 0 | T8: =IFERROR(S8/(IFERROR(LOOKUP(2,1/('Transaction Log'!H5:H106<>""),'Transaction Log'!H5:H106),0)),0) -> 0 | U8: =IFERROR(IF(J8<=0,"No Balance",IF(O8<=0,"No Withdrawal",IF(TODAY()<E8,"LOCKED",IF(O8>J8,"Exceeds Balance","Approved")))),"—") -> No Balance
A9: 4 | E9: =IFERROR(C9+D9,"") -> 0 | F9: =IFERROR(E9-TODAY(),"") -> -46096 | G9: =IFERROR(IF(TODAY()>=E9,"UNLOCKED","LOCKED"),"") -> UNLOCKED | H9: =IFERROR(SUMIF('Transaction Log'!C5:C106,B9,'Transaction Log'!E5:E106),0) -> 0 | I9: =IFERROR(SUMIF('Transaction Log'!C5:C106,B9,'Transaction Log'!F5:F106),0) -> 0 | J9: =IFERROR(H9-I9,0) -> 0 | K9: =IFERROR(J9/(IFERROR(LOOKUP(2,1/('Transaction Log'!H5:H106<>""),'Transaction Log'!H5:H106),0)),0) -> 0 | L9: =IFERROR(SUM(Positions!Q6:Q105),0) -> 1.1832186e+09 | M9: =IFERROR(K9*L9,0) -> 0 | P9: =IFERROR(O9/J9,0) -> 0 | Q9: =IFERROR(P9*M9,0) -> 0 | R9: =IFERROR(IF(O9>0,O9+Q9,""),"") | S9: =IFERROR(J9-O9,J9) -> 0 | T9: =IFERROR(S9/(IFERROR(LOOKUP(2,1/('Transaction Log'!H5:H106<>""),'Transaction Log'!H5:H106),0)),0) -> 0 | U9: =IFERROR(IF(J9<=0,"No Balance",IF(O9<=0,"No Withdrawal",IF(TODAY()<E9,"LOCKED",IF(O9>J9,"Exceeds Balance","Approved")))),"—") -> No Balance
A10: 5 | E10: =IFERROR(C10+D10,"") -> 0 | F10: =IFERROR(E10-TODAY(),"") -> -46096 | G10: =IFERROR(IF(TODAY()>=E10,"UNLOCKED","LOCKED"),"") -> UNLOCKED | H10: =IFERROR(SUMIF('Transaction Log'!C5:C106,B10,'Transaction Log'!E5:E106),0) -> 0 | I10: =IFERROR(SUMIF('Transaction Log'!C5:C106,B10,'Transaction Log'!F5:F106),0) -> 0 | J10: =IFERROR(H10-I10,0) -> 0 | K10: =IFERROR(J10/(IFERROR(LOOKUP(2,1/('Transaction Log'!H5:H106<>""),'Transaction Log'!H5:H106),0)),0) -> 0 | L10: =IFERROR(SUM(Positions!Q6:Q105),0) -> 1.1832186e+09 | M10: =IFERROR(K10*L10,0) -> 0 | P10: =IFERROR(O10/J10,0) -> 0 | Q10: =IFERROR(P10*M10,0) -> 0 | R10: =IFERROR(IF(O10>0,O10+Q10,""),"") | S10: =IFERROR(J10-O10,J10) -> 0 | T10: =IFERROR(S10/(IFERROR(LOOKUP(2,1/('Transaction Log'!H5:H106<>""),'Transaction Log'!H5:H106),0)),0) -> 0 | U10: =IFERROR(IF(J10<=0,"No Balance",IF(O10<=0,"No Withdrawal",IF(TODAY()<E10,"LOCKED",IF(O10>J10,"Exceeds Balance","Approved")))),"—") -> No Balance
A11: 6 | E11: =IFERROR(C11+D11,"") -> 0 | F11: =IFERROR(E11-TODAY(),"") -> -46096 | G11: =IFERROR(IF(TODAY()>=E11,"UNLOCKED","LOCKED"),"") -> UNLOCKED | H11: =IFERROR(SUMIF('Transaction Log'!C5:C106,B11,'Transaction Log'!E5:E106),0) -> 0 | I11: =IFERROR(SUMIF('Transaction Log'!C5:C106,B11,'Transaction Log'!F5:F106),0) -> 0 | J11: =IFERROR(H11-I11,0) -> 0 | K11: =IFERROR(J11/(IFERROR(LOOKUP(2,1/('Transaction Log'!H5:H106<>""),'Transaction Log'!H5:H106),0)),0) -> 0 | L11: =IFERROR(SUM(Positions!Q6:Q105),0) -> 1.1832186e+09 | M11: =IFERROR(K11*L11,0) -> 0 | P11: =IFERROR(O11/J11,0) -> 0 | Q11: =IFERROR(P11*M11,0) -> 0 | R11: =IFERROR(IF(O11>0,O11+Q11,""),"") | S11: =IFERROR(J11-O11,J11) -> 0 | T11: =IFERROR(S11/(IFERROR(LOOKUP(2,1/('Transaction Log'!H5:H106<>""),'Transaction Log'!H5:H106),0)),0) -> 0 | U11: =IFERROR(IF(J11<=0,"No Balance",IF(O11<=0,"No Withdrawal",IF(TODAY()<E11,"LOCKED",IF(O11>J11,"Exceeds Balance","Approved")))),"—") -> No Balance
A12: 7 | E12: =IFERROR(C12+D12,"") -> 0 | F12: =IFERROR(E12-TODAY(),"") -> -46096 | G12: =IFERROR(IF(TODAY()>=E12,"UNLOCKED","LOCKED"),"") -> UNLOCKED | H12: =IFERROR(SUMIF('Transaction Log'!C5:C106,B12,'Transaction Log'!E5:E106),0) -> 0 | I12: =IFERROR(SUMIF('Transaction Log'!C5:C106,B12,'Transaction Log'!F5:F106),0) -> 0 | J12: =IFERROR(H12-I12,0) -> 0 | K12: =IFERROR(J12/(IFERROR(LOOKUP(2,1/('Transaction Log'!H5:H106<>""),'Transaction Log'!H5:H106),0)),0) -> 0 | L12: =IFERROR(SUM(Positions!Q6:Q105),0) -> 1.1832186e+09 | M12: =IFERROR(K12*L12,0) -> 0 | P12: =IFERROR(O12/J12,0) -> 0 | Q12: =IFERROR(P12*M12,0) -> 0 | R12: =IFERROR(IF(O12>0,O12+Q12,""),"") | S12: =IFERROR(J12-O12,J12) -> 0 | T12: =IFERROR(S12/(IFERROR(LOOKUP(2,1/('Transaction Log'!H5:H106<>""),'Transaction Log'!H5:H106),0)),0) -> 0 | U12: =IFERROR(IF(J12<=0,"No Balance",IF(O12<=0,"No Withdrawal",IF(TODAY()<E12,"LOCKED",IF(O12>J12,"Exceeds Balance","Approved")))),"—") -> No Balance
A13: 8 | E13: =IFERROR(C13+D13,"") -> 0 | F13: =IFERROR(E13-TODAY(),"") -> -46096 | G13: =IFERROR(IF(TODAY()>=E13,"UNLOCKED","LOCKED"),"") -> UNLOCKED | H13: =IFERROR(SUMIF('Transaction Log'!C5:C106,B13,'Transaction Log'!E5:E106),0) -> 0 | I13: =IFERROR(SUMIF('Transaction Log'!C5:C106,B13,'Transaction Log'!F5:F106),0) -> 0 | J13: =IFERROR(H13-I13,0) -> 0 | K13: =IFERROR(J13/(IFERROR(LOOKUP(2,1/('Transaction Log'!H5:H106<>""),'Transaction Log'!H5:H106),0)),0) -> 0 | L13: =IFERROR(SUM(Positions!Q6:Q105),0) -> 1.1832186e+09 | M13: =IFERROR(K13*L13,0) -> 0 | P13: =IFERROR(O13/J13,0) -> 0 | Q13: =IFERROR(P13*M13,0) -> 0 | R13: =IFERROR(IF(O13>0,O13+Q13,""),"") | S13: =IFERROR(J13-O13,J13) -> 0 | T13: =IFERROR(S13/(IFERROR(LOOKUP(2,1/('Transaction Log'!H5:H106<>""),'Transaction Log'!H5:H106),0)),0) -> 0 | U13: =IFERROR(IF(J13<=0,"No Balance",IF(O13<=0,"No Withdrawal",IF(TODAY()<E13,"LOCKED",IF(O13>J13,"Exceeds Balance","Approved")))),"—") -> No Balance
A14: 9 | E14: =IFERROR(C14+D14,"") -> 0 | F14: =IFERROR(E14-TODAY(),"") -> -46096 | G14: =IFERROR(IF(TODAY()>=E14,"UNLOCKED","LOCKED"),"") -> UNLOCKED | H14: =IFERROR(SUMIF('Transaction Log'!C5:C106,B14,'Transaction Log'!E5:E106),0) -> 0 | I14: =IFERROR(SUMIF('Transaction Log'!C5:C106,B14,'Transaction Log'!F5:F106),0) -> 0 | J14: =IFERROR(H14-I14,0) -> 0 | K14: =IFERROR(J14/(IFERROR(LOOKUP(2,1/('Transaction Log'!H5:H106<>""),'Transaction Log'!H5:H106),0)),0) -> 0 | L14: =IFERROR(SUM(Positions!Q6:Q105),0) -> 1.1832186e+09 | M14: =IFERROR(K14*L14,0) -> 0 | P14: =IFERROR(O14/J14,0) -> 0 | Q14: =IFERROR(P14*M14,0) -> 0 | R14: =IFERROR(IF(O14>0,O14+Q14,""),"") | S14: =IFERROR(J14-O14,J14) -> 0 | T14: =IFERROR(S14/(IFERROR(LOOKUP(2,1/('Transaction Log'!H5:H106<>""),'Transaction Log'!H5:H106),0)),0) -> 0 | U14: =IFERROR(IF(J14<=0,"No Balance",IF(O14<=0,"No Withdrawal",IF(TODAY()<E14,"LOCKED",IF(O14>J14,"Exceeds Balance","Approved")))),"—") -> No Balance
A15: 10 | E15: =IFERROR(C15+D15,"") -> 0 | F15: =IFERROR(E15-TODAY(),"") -> -46096 | G15: =IFERROR(IF(TODAY()>=E15,"UNLOCKED","LOCKED"),"") -> UNLOCKED | H15: =IFERROR(SUMIF('Transaction Log'!C5:C106,B15,'Transaction Log'!E5:E106),0) -> 0 | I15: =IFERROR(SUMIF('Transaction Log'!C5:C106,B15,'Transaction Log'!F5:F106),0) -> 0 | J15: =IFERROR(H15-I15,0) -> 0 | K15: =IFERROR(J15/(IFERROR(LOOKUP(2,1/('Transaction Log'!H5:H106<>""),'Transaction Log'!H5:H106),0)),0) -> 0 | L15: =IFERROR(SUM(Positions!Q6:Q105),0) -> 1.1832186e+09 | M15: =IFERROR(K15*L15,0) -> 0 | P15: =IFERROR(O15/J15,0) -> 0 | Q15: =IFERROR(P15*M15,0) -> 0 | R15: =IFERROR(IF(O15>0,O15+Q15,""),"") | S15: =IFERROR(J15-O15,J15) -> 0 | T15: =IFERROR(S15/(IFERROR(LOOKUP(2,1/('Transaction Log'!H5:H106<>""),'Transaction Log'!H5:H106),0)),0) -> 0 | U15: =IFERROR(IF(J15<=0,"No Balance",IF(O15<=0,"No Withdrawal",IF(TODAY()<E15,"LOCKED",IF(O15>J15,"Exceeds Balance","Approved")))),"—") -> No Balance
A16: 11 | E16: =IFERROR(C16+D16,"") -> 0 | F16: =IFERROR(E16-TODAY(),"") -> -46096 | G16: =IFERROR(IF(TODAY()>=E16,"UNLOCKED","LOCKED"),"") -> UNLOCKED | H16: =IFERROR(SUMIF('Transaction Log'!C5:C106,B16,'Transaction Log'!E5:E106),0) -> 0 | I16: =IFERROR(SUMIF('Transaction Log'!C5:C106,B16,'Transaction Log'!F5:F106),0) -> 0 | J16: =IFERROR(H16-I16,0) -> 0 | K16: =IFERROR(J16/(IFERROR(LOOKUP(2,1/('Transaction Log'!H5:H106<>""),'Transaction Log'!H5:H106),0)),0) -> 0 | L16: =IFERROR(SUM(Positions!Q6:Q105),0) -> 1.1832186e+09 | M16: =IFERROR(K16*L16,0) -> 0 | P16: =IFERROR(O16/J16,0) -> 0 | Q16: =IFERROR(P16*M16,0) -> 0 | R16: =IFERROR(IF(O16>0,O16+Q16,""),"") | S16: =IFERROR(J16-O16,J16) -> 0 | T16: =IFERROR(S16/(IFERROR(LOOKUP(2,1/('Transaction Log'!H5:H106<>""),'Transaction Log'!H5:H106),0)),0) -> 0 | U16: =IFERROR(IF(J16<=0,"No Balance",IF(O16<=0,"No Withdrawal",IF(TODAY()<E16,"LOCKED",IF(O16>J16,"Exceeds Balance","Approved")))),"—") -> No Balance
A17: 12 | E17: =IFERROR(C17+D17,"") -> 0 | F17: =IFERROR(E17-TODAY(),"") -> -46096 | G17: =IFERROR(IF(TODAY()>=E17,"UNLOCKED","LOCKED"),"") -> UNLOCKED | H17: =IFERROR(SUMIF('Transaction Log'!C5:C106,B17,'Transaction Log'!E5:E106),0) -> 0 | I17: =IFERROR(SUMIF('Transaction Log'!C5:C106,B17,'Transaction Log'!F5:F106),0) -> 0 | J17: =IFERROR(H17-I17,0) -> 0 | K17: =IFERROR(J17/(IFERROR(LOOKUP(2,1/('Transaction Log'!H5:H106<>""),'Transaction Log'!H5:H106),0)),0) -> 0 | L17: =IFERROR(SUM(Positions!Q6:Q105),0) -> 1.1832186e+09 | M17: =IFERROR(K17*L17,0) -> 0 | P17: =IFERROR(O17/J17,0) -> 0 | Q17: =IFERROR(P17*M17,0) -> 0 | R17: =IFERROR(IF(O17>0,O17+Q17,""),"") | S17: =IFERROR(J17-O17,J17) -> 0 | T17: =IFERROR(S17/(IFERROR(LOOKUP(2,1/('Transaction Log'!H5:H106<>""),'Transaction Log'!H5:H106),0)),0) -> 0 | U17: =IFERROR(IF(J17<=0,"No Balance",IF(O17<=0,"No Withdrawal",IF(TODAY()<E17,"LOCKED",IF(O17>J17,"Exceeds Balance","Approved")))),"—") -> No Balance
A18: 13 | E18: =IFERROR(C18+D18,"") -> 0 | F18: =IFERROR(E18-TODAY(),"") -> -46096 | G18: =IFERROR(IF(TODAY()>=E18,"UNLOCKED","LOCKED"),"") -> UNLOCKED | H18: =IFERROR(SUMIF('Transaction Log'!C5:C106,B18,'Transaction Log'!E5:E106),0) -> 0 | I18: =IFERROR(SUMIF('Transaction Log'!C5:C106,B18,'Transaction Log'!F5:F106),0) -> 0 | J18: =IFERROR(H18-I18,0) -> 0 | K18: =IFERROR(J18/(IFERROR(LOOKUP(2,1/('Transaction Log'!H5:H106<>""),'Transaction Log'!H5:H106),0)),0) -> 0 | L18: =IFERROR(SUM(Positions!Q6:Q105),0) -> 1.1832186e+09 | M18: =IFERROR(K18*L18,0) -> 0 | P18: =IFERROR(O18/J18,0) -> 0 | Q18: =IFERROR(P18*M18,0) -> 0 | R18: =IFERROR(IF(O18>0,O18+Q18,""),"") | S18: =IFERROR(J18-O18,J18) -> 0 | T18: =IFERROR(S18/(IFERROR(LOOKUP(2,1/('Transaction Log'!H5:H106<>""),'Transaction Log'!H5:H106),0)),0) -> 0 | U18: =IFERROR(IF(J18<=0,"No Balance",IF(O18<=0,"No Withdrawal",IF(TODAY()<E18,"LOCKED",IF(O18>J18,"Exceeds Balance","Approved")))),"—") -> No Balance
A19: 14 | E19: =IFERROR(C19+D19,"") -> 0 | F19: =IFERROR(E19-TODAY(),"") -> -46096 | G19: =IFERROR(IF(TODAY()>=E19,"UNLOCKED","LOCKED"),"") -> UNLOCKED | H19: =IFERROR(SUMIF('Transaction Log'!C5:C106,B19,'Transaction Log'!E5:E106),0) -> 0 | I19: =IFERROR(SUMIF('Transaction Log'!C5:C106,B19,'Transaction Log'!F5:F106),0) -> 0 | J19: =IFERROR(H19-I19,0) -> 0 | K19: =IFERROR(J19/(IFERROR(LOOKUP(2,1/('Transaction Log'!H5:H106<>""),'Transaction Log'!H5:H106),0)),0) -> 0 | L19: =IFERROR(SUM(Positions!Q6:Q105),0) -> 1.1832186e+09 | M19: =IFERROR(K19*L19,0) -> 0 | P19: =IFERROR(O19/J19,0) -> 0 | Q19: =IFERROR(P19*M19,0) -> 0 | R19: =IFERROR(IF(O19>0,O19+Q19,""),"") | S19: =IFERROR(J19-O19,J19) -> 0 | T19: =IFERROR(S19/(IFERROR(LOOKUP(2,1/('Transaction Log'!H5:H106<>""),'Transaction Log'!H5:H106),0)),0) -> 0 | U19: =IFERROR(IF(J19<=0,"No Balance",IF(O19<=0,"No Withdrawal",IF(TODAY()<E19,"LOCKED",IF(O19>J19,"Exceeds Balance","Approved")))),"—") -> No Balance
A20: 15 | E20: =IFERROR(C20+D20,"") -> 0 | F20: =IFERROR(E20-TODAY(),"") -> -46096 | G20: =IFERROR(IF(TODAY()>=E20,"UNLOCKED","LOCKED"),"") -> UNLOCKED | H20: =IFERROR(SUMIF('Transaction Log'!C5:C106,B20,'Transaction Log'!E5:E106),0) -> 0 | I20: =IFERROR(SUMIF('Transaction Log'!C5:C106,B20,'Transaction Log'!F5:F106),0) -> 0 | J20: =IFERROR(H20-I20,0) -> 0 | K20: =IFERROR(J20/(IFERROR(LOOKUP(2,1/('Transaction Log'!H5:H106<>""),'Transaction Log'!H5:H106),0)),0) -> 0 | L20: =IFERROR(SUM(Positions!Q6:Q105),0) -> 1.1832186e+09 | M20: =IFERROR(K20*L20,0) -> 0 | P20: =IFERROR(O20/J20,0) -> 0 | Q20: =IFERROR(P20*M20,0) -> 0 | R20: =IFERROR(IF(O20>0,O20+Q20,""),"") | S20: =IFERROR(J20-O20,J20) -> 0 | T20: =IFERROR(S20/(IFERROR(LOOKUP(2,1/('Transaction Log'!H5:H106<>""),'Transaction Log'!H5:H106),0)),0) -> 0 | U20: =IFERROR(IF(J20<=0,"No Balance",IF(O20<=0,"No Withdrawal",IF(TODAY()<E20,"LOCKED",IF(O20>J20,"Exceeds Balance","Approved")))),"—") -> No Balance
A21: 16 | E21: =IFERROR(C21+D21,"") -> 0 | F21: =IFERROR(E21-TODAY(),"") -> -46096 | G21: =IFERROR(IF(TODAY()>=E21,"UNLOCKED","LOCKED"),"") -> UNLOCKED | H21: =IFERROR(SUMIF('Transaction Log'!C5:C106,B21,'Transaction Log'!E5:E106),0) -> 0 | I21: =IFERROR(SUMIF('Transaction Log'!C5:C106,B21,'Transaction Log'!F5:F106),0) -> 0 | J21: =IFERROR(H21-I21,0) -> 0 | K21: =IFERROR(J21/(IFERROR(LOOKUP(2,1/('Transaction Log'!H5:H106<>""),'Transaction Log'!H5:H106),0)),0) -> 0 | L21: =IFERROR(SUM(Positions!Q6:Q105),0) -> 1.1832186e+09 | M21: =IFERROR(K21*L21,0) -> 0 | P21: =IFERROR(O21/J21,0) -> 0 | Q21: =IFERROR(P21*M21,0) -> 0 | R21: =IFERROR(IF(O21>0,O21+Q21,""),"") | S21: =IFERROR(J21-O21,J21) -> 0 | T21: =IFERROR(S21/(IFERROR(LOOKUP(2,1/('Transaction Log'!H5:H106<>""),'Transaction Log'!H5:H106),0)),0) -> 0 | U21: =IFERROR(IF(J21<=0,"No Balance",IF(O21<=0,"No Withdrawal",IF(TODAY()<E21,"LOCKED",IF(O21>J21,"Exceeds Balance","Approved")))),"—") -> No Balance
A22: 17 | E22: =IFERROR(C22+D22,"") -> 0 | F22: =IFERROR(E22-TODAY(),"") -> -46096 | G22: =IFERROR(IF(TODAY()>=E22,"UNLOCKED","LOCKED"),"") -> UNLOCKED | H22: =IFERROR(SUMIF('Transaction Log'!C5:C106,B22,'Transaction Log'!E5:E106),0) -> 0 | I22: =IFERROR(SUMIF('Transaction Log'!C5:C106,B22,'Transaction Log'!F5:F106),0) -> 0 | J22: =IFERROR(H22-I22,0) -> 0 | K22: =IFERROR(J22/(IFERROR(LOOKUP(2,1/('Transaction Log'!H5:H106<>""),'Transaction Log'!H5:H106),0)),0) -> 0 | L22: =IFERROR(SUM(Positions!Q6:Q105),0) -> 1.1832186e+09 | M22: =IFERROR(K22*L22,0) -> 0 | P22: =IFERROR(O22/J22,0) -> 0 | Q22: =IFERROR(P22*M22,0) -> 0 | R22: =IFERROR(IF(O22>0,O22+Q22,""),"") | S22: =IFERROR(J22-O22,J22) -> 0 | T22: =IFERROR(S22/(IFERROR(LOOKUP(2,1/('Transaction Log'!H5:H106<>""),'Transaction Log'!H5:H106),0)),0) -> 0 | U22: =IFERROR(IF(J22<=0,"No Balance",IF(O22<=0,"No Withdrawal",IF(TODAY()<E22,"LOCKED",IF(O22>J22,"Exceeds Balance","Approved")))),"—") -> No Balance
A23: 18 | E23: =IFERROR(C23+D23,"") -> 0 | F23: =IFERROR(E23-TODAY(),"") -> -46096 | G23: =IFERROR(IF(TODAY()>=E23,"UNLOCKED","LOCKED"),"") -> UNLOCKED | H23: =IFERROR(SUMIF('Transaction Log'!C5:C106,B23,'Transaction Log'!E5:E106),0) -> 0 | I23: =IFERROR(SUMIF('Transaction Log'!C5:C106,B23,'Transaction Log'!F5:F106),0) -> 0 | J23: =IFERROR(H23-I23,0) -> 0 | K23: =IFERROR(J23/(IFERROR(LOOKUP(2,1/('Transaction Log'!H5:H106<>""),'Transaction Log'!H5:H106),0)),0) -> 0 | L23: =IFERROR(SUM(Positions!Q6:Q105),0) -> 1.1832186e+09 | M23: =IFERROR(K23*L23,0) -> 0 | P23: =IFERROR(O23/J23,0) -> 0 | Q23: =IFERROR(P23*M23,0) -> 0 | R23: =IFERROR(IF(O23>0,O23+Q23,""),"") | S23: =IFERROR(J23-O23,J23) -> 0 | T23: =IFERROR(S23/(IFERROR(LOOKUP(2,1/('Transaction Log'!H5:H106<>""),'Transaction Log'!H5:H106),0)),0) -> 0 | U23: =IFERROR(IF(J23<=0,"No Balance",IF(O23<=0,"No Withdrawal",IF(TODAY()<E23,"LOCKED",IF(O23>J23,"Exceeds Balance","Approved")))),"—") -> No Balance
A24: 19 | E24: =IFERROR(C24+D24,"") -> 0 | F24: =IFERROR(E24-TODAY(),"") -> -46096 | G24: =IFERROR(IF(TODAY()>=E24,"UNLOCKED","LOCKED"),"") -> UNLOCKED | H24: =IFERROR(SUMIF('Transaction Log'!C5:C106,B24,'Transaction Log'!E5:E106),0) -> 0 | I24: =IFERROR(SUMIF('Transaction Log'!C5:C106,B24,'Transaction Log'!F5:F106),0) -> 0 | J24: =IFERROR(H24-I24,0) -> 0 | K24: =IFERROR(J24/(IFERROR(LOOKUP(2,1/('Transaction Log'!H5:H106<>""),'Transaction Log'!H5:H106),0)),0) -> 0 | L24: =IFERROR(SUM(Positions!Q6:Q105),0) -> 1.1832186e+09 | M24: =IFERROR(K24*L24,0) -> 0 | P24: =IFERROR(O24/J24,0) -> 0 | Q24: =IFERROR(P24*M24,0) -> 0 | R24: =IFERROR(IF(O24>0,O24+Q24,""),"") | S24: =IFERROR(J24-O24,J24) -> 0 | T24: =IFERROR(S24/(IFERROR(LOOKUP(2,1/('Transaction Log'!H5:H106<>""),'Transaction Log'!H5:H106),0)),0) -> 0 | U24: =IFERROR(IF(J24<=0,"No Balance",IF(O24<=0,"No Withdrawal",IF(TODAY()<E24,"LOCKED",IF(O24>J24,"Exceeds Balance","Approved")))),"—") -> No Balance
A25: 20 | E25: =IFERROR(C25+D25,"") -> 0 | F25: =IFERROR(E25-TODAY(),"") -> -46096 | G25: =IFERROR(IF(TODAY()>=E25,"UNLOCKED","LOCKED"),"") -> UNLOCKED | H25: =IFERROR(SUMIF('Transaction Log'!C5:C106,B25,'Transaction Log'!E5:E106),0) -> 0 | I25: =IFERROR(SUMIF('Transaction Log'!C5:C106,B25,'Transaction Log'!F5:F106),0) -> 0 | J25: =IFERROR(H25-I25,0) -> 0 | K25: =IFERROR(J25/(IFERROR(LOOKUP(2,1/('Transaction Log'!H5:H106<>""),'Transaction Log'!H5:H106),0)),0) -> 0 | L25: =IFERROR(SUM(Positions!Q6:Q105),0) -> 1.1832186e+09 | M25: =IFERROR(K25*L25,0) -> 0 | P25: =IFERROR(O25/J25,0) -> 0 | Q25: =IFERROR(P25*M25,0) -> 0 | R25: =IFERROR(IF(O25>0,O25+Q25,""),"") | S25: =IFERROR(J25-O25,J25) -> 0 | T25: =IFERROR(S25/(IFERROR(LOOKUP(2,1/('Transaction Log'!H5:H106<>""),'Transaction Log'!H5:H106),0)),0) -> 0 | U25: =IFERROR(IF(J25<=0,"No Balance",IF(O25<=0,"No Withdrawal",IF(TODAY()<E25,"LOCKED",IF(O25>J25,"Exceeds Balance","Approved")))),"—") -> No Balance
A26: 21 | E26: =IFERROR(C26+D26,"") -> 0 | F26: =IFERROR(E26-TODAY(),"") -> -46096 | G26: =IFERROR(IF(TODAY()>=E26,"UNLOCKED","LOCKED"),"") -> UNLOCKED | H26: =IFERROR(SUMIF('Transaction Log'!C5:C106,B26,'Transaction Log'!E5:E106),0) -> 0 | I26: =IFERROR(SUMIF('Transaction Log'!C5:C106,B26,'Transaction Log'!F5:F106),0) -> 0 | J26: =IFERROR(H26-I26,0) -> 0 | K26: =IFERROR(J26/(IFERROR(LOOKUP(2,1/('Transaction Log'!H5:H106<>""),'Transaction Log'!H5:H106),0)),0) -> 0 | L26: =IFERROR(SUM(Positions!Q6:Q105),0) -> 1.1832186e+09 | M26: =IFERROR(K26*L26,0) -> 0 | P26: =IFERROR(O26/J26,0) -> 0 | Q26: =IFERROR(P26*M26,0) -> 0 | R26: =IFERROR(IF(O26>0,O26+Q26,""),"") | S26: =IFERROR(J26-O26,J26) -> 0 | T26: =IFERROR(S26/(IFERROR(LOOKUP(2,1/('Transaction Log'!H5:H106<>""),'Transaction Log'!H5:H106),0)),0) -> 0 | U26: =IFERROR(IF(J26<=0,"No Balance",IF(O26<=0,"No Withdrawal",IF(TODAY()<E26,"LOCKED",IF(O26>J26,"Exceeds Balance","Approved")))),"—") -> No Balance
A27: 22 | E27: =IFERROR(C27+D27,"") -> 0 | F27: =IFERROR(E27-TODAY(),"") -> -46096 | G27: =IFERROR(IF(TODAY()>=E27,"UNLOCKED","LOCKED"),"") -> UNLOCKED | H27: =IFERROR(SUMIF('Transaction Log'!C5:C106,B27,'Transaction Log'!E5:E106),0) -> 0 | I27: =IFERROR(SUMIF('Transaction Log'!C5:C106,B27,'Transaction Log'!F5:F106),0) -> 0 | J27: =IFERROR(H27-I27,0) -> 0 | K27: =IFERROR(J27/(IFERROR(LOOKUP(2,1/('Transaction Log'!H5:H106<>""),'Transaction Log'!H5:H106),0)),0) -> 0 | L27: =IFERROR(SUM(Positions!Q6:Q105),0) -> 1.1832186e+09 | M27: =IFERROR(K27*L27,0) -> 0 | P27: =IFERROR(O27/J27,0) -> 0 | Q27: =IFERROR(P27*M27,0) -> 0 | R27: =IFERROR(IF(O27>0,O27+Q27,""),"") | S27: =IFERROR(J27-O27,J27) -> 0 | T27: =IFERROR(S27/(IFERROR(LOOKUP(2,1/('Transaction Log'!H5:H106<>""),'Transaction Log'!H5:H106),0)),0) -> 0 | U27: =IFERROR(IF(J27<=0,"No Balance",IF(O27<=0,"No Withdrawal",IF(TODAY()<E27,"LOCKED",IF(O27>J27,"Exceeds Balance","Approved")))),"—") -> No Balance
A28: 23 | E28: =IFERROR(C28+D28,"") -> 0 | F28: =IFERROR(E28-TODAY(),"") -> -46096 | G28: =IFERROR(IF(TODAY()>=E28,"UNLOCKED","LOCKED"),"") -> UNLOCKED | H28: =IFERROR(SUMIF('Transaction Log'!C5:C106,B28,'Transaction Log'!E5:E106),0) -> 0 | I28: =IFERROR(SUMIF('Transaction Log'!C5:C106,B28,'Transaction Log'!F5:F106),0) -> 0 | J28: =IFERROR(H28-I28,0) -> 0 | K28: =IFERROR(J28/(IFERROR(LOOKUP(2,1/('Transaction Log'!H5:H106<>""),'Transaction Log'!H5:H106),0)),0) -> 0 | L28: =IFERROR(SUM(Positions!Q6:Q105),0) -> 1.1832186e+09 | M28: =IFERROR(K28*L28,0) -> 0 | P28: =IFERROR(O28/J28,0) -> 0 | Q28: =IFERROR(P28*M28,0) -> 0 | R28: =IFERROR(IF(O28>0,O28+Q28,""),"") | S28: =IFERROR(J28-O28,J28) -> 0 | T28: =IFERROR(S28/(IFERROR(LOOKUP(2,1/('Transaction Log'!H5:H106<>""),'Transaction Log'!H5:H106),0)),0) -> 0 | U28: =IFERROR(IF(J28<=0,"No Balance",IF(O28<=0,"No Withdrawal",IF(TODAY()<E28,"LOCKED",IF(O28>J28,"Exceeds Balance","Approved")))),"—") -> No Balance
A29: 24 | E29: =IFERROR(C29+D29,"") -> 0 | F29: =IFERROR(E29-TODAY(),"") -> -46096 | G29: =IFERROR(IF(TODAY()>=E29,"UNLOCKED","LOCKED"),"") -> UNLOCKED | H29: =IFERROR(SUMIF('Transaction Log'!C5:C106,B29,'Transaction Log'!E5:E106),0) -> 0 | I29: =IFERROR(SUMIF('Transaction Log'!C5:C106,B29,'Transaction Log'!F5:F106),0) -> 0 | J29: =IFERROR(H29-I29,0) -> 0 | K29: =IFERROR(J29/(IFERROR(LOOKUP(2,1/('Transaction Log'!H5:H106<>""),'Transaction Log'!H5:H106),0)),0) -> 0 | L29: =IFERROR(SUM(Positions!Q6:Q105),0) -> 1.1832186e+09 | M29: =IFERROR(K29*L29,0) -> 0 | P29: =IFERROR(O29/J29,0) -> 0 | Q29: =IFERROR(P29*M29,0) -> 0 | R29: =IFERROR(IF(O29>0,O29+Q29,""),"") | S29: =IFERROR(J29-O29,J29) -> 0 | T29: =IFERROR(S29/(IFERROR(LOOKUP(2,1/('Transaction Log'!H5:H106<>""),'Transaction Log'!H5:H106),0)),0) -> 0 | U29: =IFERROR(IF(J29<=0,"No Balance",IF(O29<=0,"No Withdrawal",IF(TODAY()<E29,"LOCKED",IF(O29>J29,"Exceeds Balance","Approved")))),"—") -> No Balance
A30: 25 | E30: =IFERROR(C30+D30,"") -> 0 | F30: =IFERROR(E30-TODAY(),"") -> -46096 | G30: =IFERROR(IF(TODAY()>=E30,"UNLOCKED","LOCKED"),"") -> UNLOCKED | H30: =IFERROR(SUMIF('Transaction Log'!C5:C106,B30,'Transaction Log'!E5:E106),0) -> 0 | I30: =IFERROR(SUMIF('Transaction Log'!C5:C106,B30,'Transaction Log'!F5:F106),0) -> 0 | J30: =IFERROR(H30-I30,0) -> 0 | K30: =IFERROR(J30/(IFERROR(LOOKUP(2,1/('Transaction Log'!H5:H106<>""),'Transaction Log'!H5:H106),0)),0) -> 0 | L30: =IFERROR(SUM(Positions!Q6:Q105),0) -> 1.1832186e+09 | M30: =IFERROR(K30*L30,0) -> 0 | P30: =IFERROR(O30/J30,0) -> 0 | Q30: =IFERROR(P30*M30,0) -> 0 | R30: =IFERROR(IF(O30>0,O30+Q30,""),"") | S30: =IFERROR(J30-O30,J30) -> 0 | T30: =IFERROR(S30/(IFERROR(LOOKUP(2,1/('Transaction Log'!H5:H106<>""),'Transaction Log'!H5:H106),0)),0) -> 0 | U30: =IFERROR(IF(J30<=0,"No Balance",IF(O30<=0,"No Withdrawal",IF(TODAY()<E30,"LOCKED",IF(O30>J30,"Exceeds Balance","Approved")))),"—") -> No Balance
A31: 26 | E31: =IFERROR(C31+D31,"") -> 0 | F31: =IFERROR(E31-TODAY(),"") -> -46096 | G31: =IFERROR(IF(TODAY()>=E31,"UNLOCKED","LOCKED"),"") -> UNLOCKED | H31: =IFERROR(SUMIF('Transaction Log'!C5:C106,B31,'Transaction Log'!E5:E106),0) -> 0 | I31: =IFERROR(SUMIF('Transaction Log'!C5:C106,B31,'Transaction Log'!F5:F106),0) -> 0 | J31: =IFERROR(H31-I31,0) -> 0 | K31: =IFERROR(J31/(IFERROR(LOOKUP(2,1/('Transaction Log'!H5:H106<>""),'Transaction Log'!H5:H106),0)),0) -> 0 | L31: =IFERROR(SUM(Positions!Q6:Q105),0) -> 1.1832186e+09 | M31: =IFERROR(K31*L31,0) -> 0 | P31: =IFERROR(O31/J31,0) -> 0 | Q31: =IFERROR(P31*M31,0) -> 0 | R31: =IFERROR(IF(O31>0,O31+Q31,""),"") | S31: =IFERROR(J31-O31,J31) -> 0 | T31: =IFERROR(S31/(IFERROR(LOOKUP(2,1/('Transaction Log'!H5:H106<>""),'Transaction Log'!H5:H106),0)),0) -> 0 | U31: =IFERROR(IF(J31<=0,"No Balance",IF(O31<=0,"No Withdrawal",IF(TODAY()<E31,"LOCKED",IF(O31>J31,"Exceeds Balance","Approved")))),"—") -> No Balance
A32: 27 | E32: =IFERROR(C32+D32,"") -> 0 | F32: =IFERROR(E32-TODAY(),"") -> -46096 | G32: =IFERROR(IF(TODAY()>=E32,"UNLOCKED","LOCKED"),"") -> UNLOCKED | H32: =IFERROR(SUMIF('Transaction Log'!C5:C106,B32,'Transaction Log'!E5:E106),0) -> 0 | I32: =IFERROR(SUMIF('Transaction Log'!C5:C106,B32,'Transaction Log'!F5:F106),0) -> 0 | J32: =IFERROR(H32-I32,0) -> 0 | K32: =IFERROR(J32/(IFERROR(LOOKUP(2,1/('Transaction Log'!H5:H106<>""),'Transaction Log'!H5:H106),0)),0) -> 0 | L32: =IFERROR(SUM(Positions!Q6:Q105),0) -> 1.1832186e+09 | M32: =IFERROR(K32*L32,0) -> 0 | P32: =IFERROR(O32/J32,0) -> 0 | Q32: =IFERROR(P32*M32,0) -> 0 | R32: =IFERROR(IF(O32>0,O32+Q32,""),"") | S32: =IFERROR(J32-O32,J32) -> 0 | T32: =IFERROR(S32/(IFERROR(LOOKUP(2,1/('Transaction Log'!H5:H106<>""),'Transaction Log'!H5:H106),0)),0) -> 0 | U32: =IFERROR(IF(J32<=0,"No Balance",IF(O32<=0,"No Withdrawal",IF(TODAY()<E32,"LOCKED",IF(O32>J32,"Exceeds Balance","Approved")))),"—") -> No Balance
A33: 28 | E33: =IFERROR(C33+D33,"") -> 0 | F33: =IFERROR(E33-TODAY(),"") -> -46096 | G33: =IFERROR(IF(TODAY()>=E33,"UNLOCKED","LOCKED"),"") -> UNLOCKED | H33: =IFERROR(SUMIF('Transaction Log'!C5:C106,B33,'Transaction Log'!E5:E106),0) -> 0 | I33: =IFERROR(SUMIF('Transaction Log'!C5:C106,B33,'Transaction Log'!F5:F106),0) -> 0 | J33: =IFERROR(H33-I33,0) -> 0 | K33: =IFERROR(J33/(IFERROR(LOOKUP(2,1/('Transaction Log'!H5:H106<>""),'Transaction Log'!H5:H106),0)),0) -> 0 | L33: =IFERROR(SUM(Positions!Q6:Q105),0) -> 1.1832186e+09 | M33: =IFERROR(K33*L33,0) -> 0 | P33: =IFERROR(O33/J33,0) -> 0 | Q33: =IFERROR(P33*M33,0) -> 0 | R33: =IFERROR(IF(O33>0,O33+Q33,""),"") | S33: =IFERROR(J33-O33,J33) -> 0 | T33: =IFERROR(S33/(IFERROR(LOOKUP(2,1/('Transaction Log'!H5:H106<>""),'Transaction Log'!H5:H106),0)),0) -> 0 | U33: =IFERROR(IF(J33<=0,"No Balance",IF(O33<=0,"No Withdrawal",IF(TODAY()<E33,"LOCKED",IF(O33>J33,"Exceeds Balance","Approved")))),"—") -> No Balance
A34: 29 | E34: =IFERROR(C34+D34,"") -> 0 | F34: =IFERROR(E34-TODAY(),"") -> -46096 | G34: =IFERROR(IF(TODAY()>=E34,"UNLOCKED","LOCKED"),"") -> UNLOCKED | H34: =IFERROR(SUMIF('Transaction Log'!C5:C106,B34,'Transaction Log'!E5:E106),0) -> 0 | I34: =IFERROR(SUMIF('Transaction Log'!C5:C106,B34,'Transaction Log'!F5:F106),0) -> 0 | J34: =IFERROR(H34-I34,0) -> 0 | K34: =IFERROR(J34/(IFERROR(LOOKUP(2,1/('Transaction Log'!H5:H106<>""),'Transaction Log'!H5:H106),0)),0) -> 0 | L34: =IFERROR(SUM(Positions!Q6:Q105),0) -> 1.1832186e+09 | M34: =IFERROR(K34*L34,0) -> 0 | P34: =IFERROR(O34/J34,0) -> 0 | Q34: =IFERROR(P34*M34,0) -> 0 | R34: =IFERROR(IF(O34>0,O34+Q34,""),"") | S34: =IFERROR(J34-O34,J34) -> 0 | T34: =IFERROR(S34/(IFERROR(LOOKUP(2,1/('Transaction Log'!H5:H106<>""),'Transaction Log'!H5:H106),0)),0) -> 0 | U34: =IFERROR(IF(J34<=0,"No Balance",IF(O34<=0,"No Withdrawal",IF(TODAY()<E34,"LOCKED",IF(O34>J34,"Exceeds Balance","Approved")))),"—") -> No Balance
A35: 30 | E35: =IFERROR(C35+D35,"") -> 0 | F35: =IFERROR(E35-TODAY(),"") -> -46096 | G35: =IFERROR(IF(TODAY()>=E35,"UNLOCKED","LOCKED"),"") -> UNLOCKED | H35: =IFERROR(SUMIF('Transaction Log'!C5:C106,B35,'Transaction Log'!E5:E106),0) -> 0 | I35: =IFERROR(SUMIF('Transaction Log'!C5:C106,B35,'Transaction Log'!F5:F106),0) -> 0 | J35: =IFERROR(H35-I35,0) -> 0 | K35: =IFERROR(J35/(IFERROR(LOOKUP(2,1/('Transaction Log'!H5:H106<>""),'Transaction Log'!H5:H106),0)),0) -> 0 | L35: =IFERROR(SUM(Positions!Q6:Q105),0) -> 1.1832186e+09 | M35: =IFERROR(K35*L35,0) -> 0 | P35: =IFERROR(O35/J35,0) -> 0 | Q35: =IFERROR(P35*M35,0) -> 0 | R35: =IFERROR(IF(O35>0,O35+Q35,""),"") | S35: =IFERROR(J35-O35,J35) -> 0 | T35: =IFERROR(S35/(IFERROR(LOOKUP(2,1/('Transaction Log'!H5:H106<>""),'Transaction Log'!H5:H106),0)),0) -> 0 | U35: =IFERROR(IF(J35<=0,"No Balance",IF(O35<=0,"No Withdrawal",IF(TODAY()<E35,"LOCKED",IF(O35>J35,"Exceeds Balance","Approved")))),"—") -> No Balance
A36: 31 | E36: =IFERROR(C36+D36,"") -> 0 | F36: =IFERROR(E36-TODAY(),"") -> -46096 | G36: =IFERROR(IF(TODAY()>=E36,"UNLOCKED","LOCKED"),"") -> UNLOCKED | H36: =IFERROR(SUMIF('Transaction Log'!C5:C106,B36,'Transaction Log'!E5:E106),0) -> 0 | I36: =IFERROR(SUMIF('Transaction Log'!C5:C106,B36,'Transaction Log'!F5:F106),0) -> 0 | J36: =IFERROR(H36-I36,0) -> 0 | K36: =IFERROR(J36/(IFERROR(LOOKUP(2,1/('Transaction Log'!H5:H106<>""),'Transaction Log'!H5:H106),0)),0) -> 0 | L36: =IFERROR(SUM(Positions!Q6:Q105),0) -> 1.1832186e+09 | M36: =IFERROR(K36*L36,0) -> 0 | P36: =IFERROR(O36/J36,0) -> 0 | Q36: =IFERROR(P36*M36,0) -> 0 | R36: =IFERROR(IF(O36>0,O36+Q36,""),"") | S36: =IFERROR(J36-O36,J36) -> 0 | T36: =IFERROR(S36/(IFERROR(LOOKUP(2,1/('Transaction Log'!H5:H106<>""),'Transaction Log'!H5:H106),0)),0) -> 0 | U36: =IFERROR(IF(J36<=0,"No Balance",IF(O36<=0,"No Withdrawal",IF(TODAY()<E36,"LOCKED",IF(O36>J36,"Exceeds Balance","Approved")))),"—") -> No Balance
A37: 32 | E37: =IFERROR(C37+D37,"") -> 0 | F37: =IFERROR(E37-TODAY(),"") -> -46096 | G37: =IFERROR(IF(TODAY()>=E37,"UNLOCKED","LOCKED"),"") -> UNLOCKED | H37: =IFERROR(SUMIF('Transaction Log'!C5:C106,B37,'Transaction Log'!E5:E106),0) -> 0 | I37: =IFERROR(SUMIF('Transaction Log'!C5:C106,B37,'Transaction Log'!F5:F106),0) -> 0 | J37: =IFERROR(H37-I37,0) -> 0 | K37: =IFERROR(J37/(IFERROR(LOOKUP(2,1/('Transaction Log'!H5:H106<>""),'Transaction Log'!H5:H106),0)),0) -> 0 | L37: =IFERROR(SUM(Positions!Q6:Q105),0) -> 1.1832186e+09 | M37: =IFERROR(K37*L37,0) -> 0 | P37: =IFERROR(O37/J37,0) -> 0 | Q37: =IFERROR(P37*M37,0) -> 0 | R37: =IFERROR(IF(O37>0,O37+Q37,""),"") | S37: =IFERROR(J37-O37,J37) -> 0 | T37: =IFERROR(S37/(IFERROR(LOOKUP(2,1/('Transaction Log'!H5:H106<>""),'Transaction Log'!H5:H106),0)),0) -> 0 | U37: =IFERROR(IF(J37<=0,"No Balance",IF(O37<=0,"No Withdrawal",IF(TODAY()<E37,"LOCKED",IF(O37>J37,"Exceeds Balance","Approved")))),"—") -> No Balance
A38: 33 | E38: =IFERROR(C38+D38,"") -> 0 | F38: =IFERROR(E38-TODAY(),"") -> -46096 | G38: =IFERROR(IF(TODAY()>=E38,"UNLOCKED","LOCKED"),"") -> UNLOCKED | H38: =IFERROR(SUMIF('Transaction Log'!C5:C106,B38,'Transaction Log'!E5:E106),0) -> 0 | I38: =IFERROR(SUMIF('Transaction Log'!C5:C106,B38,'Transaction Log'!F5:F106),0) -> 0 | J38: =IFERROR(H38-I38,0) -> 0 | K38: =IFERROR(J38/(IFERROR(LOOKUP(2,1/('Transaction Log'!H5:H106<>""),'Transaction Log'!H5:H106),0)),0) -> 0 | L38: =IFERROR(SUM(Positions!Q6:Q105),0) -> 1.1832186e+09 | M38: =IFERROR(K38*L38,0) -> 0 | P38: =IFERROR(O38/J38,0) -> 0 | Q38: =IFERROR(P38*M38,0) -> 0 | R38: =IFERROR(IF(O38>0,O38+Q38,""),"") | S38: =IFERROR(J38-O38,J38) -> 0 | T38: =IFERROR(S38/(IFERROR(LOOKUP(2,1/('Transaction Log'!H5:H106<>""),'Transaction Log'!H5:H106),0)),0) -> 0 | U38: =IFERROR(IF(J38<=0,"No Balance",IF(O38<=0,"No Withdrawal",IF(TODAY()<E38,"LOCKED",IF(O38>J38,"Exceeds Balance","Approved")))),"—") -> No Balance
A39: 34 | E39: =IFERROR(C39+D39,"") -> 0 | F39: =IFERROR(E39-TODAY(),"") -> -46096 | G39: =IFERROR(IF(TODAY()>=E39,"UNLOCKED","LOCKED"),"") -> UNLOCKED | H39: =IFERROR(SUMIF('Transaction Log'!C5:C106,B39,'Transaction Log'!E5:E106),0) -> 0 | I39: =IFERROR(SUMIF('Transaction Log'!C5:C106,B39,'Transaction Log'!F5:F106),0) -> 0 | J39: =IFERROR(H39-I39,0) -> 0 | K39: =IFERROR(J39/(IFERROR(LOOKUP(2,1/('Transaction Log'!H5:H106<>""),'Transaction Log'!H5:H106),0)),0) -> 0 | L39: =IFERROR(SUM(Positions!Q6:Q105),0) -> 1.1832186e+09 | M39: =IFERROR(K39*L39,0) -> 0 | P39: =IFERROR(O39/J39,0) -> 0 | Q39: =IFERROR(P39*M39,0) -> 0 | R39: =IFERROR(IF(O39>0,O39+Q39,""),"") | S39: =IFERROR(J39-O39,J39) -> 0 | T39: =IFERROR(S39/(IFERROR(LOOKUP(2,1/('Transaction Log'!H5:H106<>""),'Transaction Log'!H5:H106),0)),0) -> 0 | U39: =IFERROR(IF(J39<=0,"No Balance",IF(O39<=0,"No Withdrawal",IF(TODAY()<E39,"LOCKED",IF(O39>J39,"Exceeds Balance","Approved")))),"—") -> No Balance
A40: 35 | E40: =IFERROR(C40+D40,"") -> 0 | F40: =IFERROR(E40-TODAY(),"") -> -46096 | G40: =IFERROR(IF(TODAY()>=E40,"UNLOCKED","LOCKED"),"") -> UNLOCKED | H40: =IFERROR(SUMIF('Transaction Log'!C5:C106,B40,'Transaction Log'!E5:E106),0) -> 0 | I40: =IFERROR(SUMIF('Transaction Log'!C5:C106,B40,'Transaction Log'!F5:F106),0) -> 0 | J40: =IFERROR(H40-I40,0) -> 0 | K40: =IFERROR(J40/(IFERROR(LOOKUP(2,1/('Transaction Log'!H5:H106<>""),'Transaction Log'!H5:H106),0)),0) -> 0 | L40: =IFERROR(SUM(Positions!Q6:Q105),0) -> 1.1832186e+09 | M40: =IFERROR(K40*L40,0) -> 0 | P40: =IFERROR(O40/J40,0) -> 0 | Q40: =IFERROR(P40*M40,0) -> 0 | R40: =IFERROR(IF(O40>0,O40+Q40,""),"") | S40: =IFERROR(J40-O40,J40) -> 0 | T40: =IFERROR(S40/(IFERROR(LOOKUP(2,1/('Transaction Log'!H5:H106<>""),'Transaction Log'!H5:H106),0)),0) -> 0 | U40: =IFERROR(IF(J40<=0,"No Balance",IF(O40<=0,"No Withdrawal",IF(TODAY()<E40,"LOCKED",IF(O40>J40,"Exceeds Balance","Approved")))),"—") -> No Balance
A41: 36 | E41: =IFERROR(C41+D41,"") -> 0 | F41: =IFERROR(E41-TODAY(),"") -> -46096 | G41: =IFERROR(IF(TODAY()>=E41,"UNLOCKED","LOCKED"),"") -> UNLOCKED | H41: =IFERROR(SUMIF('Transaction Log'!C5:C106,B41,'Transaction Log'!E5:E106),0) -> 0 | I41: =IFERROR(SUMIF('Transaction Log'!C5:C106,B41,'Transaction Log'!F5:F106),0) -> 0 | J41: =IFERROR(H41-I41,0) -> 0 | K41: =IFERROR(J41/(IFERROR(LOOKUP(2,1/('Transaction Log'!H5:H106<>""),'Transaction Log'!H5:H106),0)),0) -> 0 | L41: =IFERROR(SUM(Positions!Q6:Q105),0) -> 1.1832186e+09 | M41: =IFERROR(K41*L41,0) -> 0 | P41: =IFERROR(O41/J41,0) -> 0 | Q41: =IFERROR(P41*M41,0) -> 0 | R41: =IFERROR(IF(O41>0,O41+Q41,""),"") | S41: =IFERROR(J41-O41,J41) -> 0 | T41: =IFERROR(S41/(IFERROR(LOOKUP(2,1/('Transaction Log'!H5:H106<>""),'Transaction Log'!H5:H106),0)),0) -> 0 | U41: =IFERROR(IF(J41<=0,"No Balance",IF(O41<=0,"No Withdrawal",IF(TODAY()<E41,"LOCKED",IF(O41>J41,"Exceeds Balance","Approved")))),"—") -> No Balance
A42: 37 | E42: =IFERROR(C42+D42,"") -> 0 | F42: =IFERROR(E42-TODAY(),"") -> -46096 | G42: =IFERROR(IF(TODAY()>=E42,"UNLOCKED","LOCKED"),"") -> UNLOCKED | H42: =IFERROR(SUMIF('Transaction Log'!C5:C106,B42,'Transaction Log'!E5:E106),0) -> 0 | I42: =IFERROR(SUMIF('Transaction Log'!C5:C106,B42,'Transaction Log'!F5:F106),0) -> 0 | J42: =IFERROR(H42-I42,0) -> 0 | K42: =IFERROR(J42/(IFERROR(LOOKUP(2,1/('Transaction Log'!H5:H106<>""),'Transaction Log'!H5:H106),0)),0) -> 0 | L42: =IFERROR(SUM(Positions!Q6:Q105),0) -> 1.1832186e+09 | M42: =IFERROR(K42*L42,0) -> 0 | P42: =IFERROR(O42/J42,0) -> 0 | Q42: =IFERROR(P42*M42,0) -> 0 | R42: =IFERROR(IF(O42>0,O42+Q42,""),"") | S42: =IFERROR(J42-O42,J42) -> 0 | T42: =IFERROR(S42/(IFERROR(LOOKUP(2,1/('Transaction Log'!H5:H106<>""),'Transaction Log'!H5:H106),0)),0) -> 0 | U42: =IFERROR(IF(J42<=0,"No Balance",IF(O42<=0,"No Withdrawal",IF(TODAY()<E42,"LOCKED",IF(O42>J42,"Exceeds Balance","Approved")))),"—") -> No Balance
A43: 38 | E43: =IFERROR(C43+D43,"") -> 0 | F43: =IFERROR(E43-TODAY(),"") -> -46096 | G43: =IFERROR(IF(TODAY()>=E43,"UNLOCKED","LOCKED"),"") -> UNLOCKED | H43: =IFERROR(SUMIF('Transaction Log'!C5:C106,B43,'Transaction Log'!E5:E106),0) -> 0 | I43: =IFERROR(SUMIF('Transaction Log'!C5:C106,B43,'Transaction Log'!F5:F106),0) -> 0 | J43: =IFERROR(H43-I43,0) -> 0 | K43: =IFERROR(J43/(IFERROR(LOOKUP(2,1/('Transaction Log'!H5:H106<>""),'Transaction Log'!H5:H106),0)),0) -> 0 | L43: =IFERROR(SUM(Positions!Q6:Q105),0) -> 1.1832186e+09 | M43: =IFERROR(K43*L43,0) -> 0 | P43: =IFERROR(O43/J43,0) -> 0 | Q43: =IFERROR(P43*M43,0) -> 0 | R43: =IFERROR(IF(O43>0,O43+Q43,""),"") | S43: =IFERROR(J43-O43,J43) -> 0 | T43: =IFERROR(S43/(IFERROR(LOOKUP(2,1/('Transaction Log'!H5:H106<>""),'Transaction Log'!H5:H106),0)),0) -> 0 | U43: =IFERROR(IF(J43<=0,"No Balance",IF(O43<=0,"No Withdrawal",IF(TODAY()<E43,"LOCKED",IF(O43>J43,"Exceeds Balance","Approved")))),"—") -> No Balance
A44: 39 | E44: =IFERROR(C44+D44,"") -> 0 | F44: =IFERROR(E44-TODAY(),"") -> -46096 | G44: =IFERROR(IF(TODAY()>=E44,"UNLOCKED","LOCKED"),"") -> UNLOCKED | H44: =IFERROR(SUMIF('Transaction Log'!C5:C106,B44,'Transaction Log'!E5:E106),0) -> 0 | I44: =IFERROR(SUMIF('Transaction Log'!C5:C106,B44,'Transaction Log'!F5:F106),0) -> 0 | J44: =IFERROR(H44-I44,0) -> 0 | K44: =IFERROR(J44/(IFERROR(LOOKUP(2,1/('Transaction Log'!H5:H106<>""),'Transaction Log'!H5:H106),0)),0) -> 0 | L44: =IFERROR(SUM(Positions!Q6:Q105),0) -> 1.1832186e+09 | M44: =IFERROR(K44*L44,0) -> 0 | P44: =IFERROR(O44/J44,0) -> 0 | Q44: =IFERROR(P44*M44,0) -> 0 | R44: =IFERROR(IF(O44>0,O44+Q44,""),"") | S44: =IFERROR(J44-O44,J44) -> 0 | T44: =IFERROR(S44/(IFERROR(LOOKUP(2,1/('Transaction Log'!H5:H106<>""),'Transaction Log'!H5:H106),0)),0) -> 0 | U44: =IFERROR(IF(J44<=0,"No Balance",IF(O44<=0,"No Withdrawal",IF(TODAY()<E44,"LOCKED",IF(O44>J44,"Exceeds Balance","Approved")))),"—") -> No Balance
A45: 40 | E45: =IFERROR(C45+D45,"") -> 0 | F45: =IFERROR(E45-TODAY(),"") -> -46096 | G45: =IFERROR(IF(TODAY()>=E45,"UNLOCKED","LOCKED"),"") -> UNLOCKED | H45: =IFERROR(SUMIF('Transaction Log'!C5:C106,B45,'Transaction Log'!E5:E106),0) -> 0 | I45: =IFERROR(SUMIF('Transaction Log'!C5:C106,B45,'Transaction Log'!F5:F106),0) -> 0 | J45: =IFERROR(H45-I45,0) -> 0 | K45: =IFERROR(J45/(IFERROR(LOOKUP(2,1/('Transaction Log'!H5:H106<>""),'Transaction Log'!H5:H106),0)),0) -> 0 | L45: =IFERROR(SUM(Positions!Q6:Q105),0) -> 1.1832186e+09 | M45: =IFERROR(K45*L45,0) -> 0 | P45: =IFERROR(O45/J45,0) -> 0 | Q45: =IFERROR(P45*M45,0) -> 0 | R45: =IFERROR(IF(O45>0,O45+Q45,""),"") | S45: =IFERROR(J45-O45,J45) -> 0 | T45: =IFERROR(S45/(IFERROR(LOOKUP(2,1/('Transaction Log'!H5:H106<>""),'Transaction Log'!H5:H106),0)),0) -> 0 | U45: =IFERROR(IF(J45<=0,"No Balance",IF(O45<=0,"No Withdrawal",IF(TODAY()<E45,"LOCKED",IF(O45>J45,"Exceeds Balance","Approved")))),"—") -> No Balance
A46: 41 | E46: =IFERROR(C46+D46,"") -> 0 | F46: =IFERROR(E46-TODAY(),"") -> -46096 | G46: =IFERROR(IF(TODAY()>=E46,"UNLOCKED","LOCKED"),"") -> UNLOCKED | H46: =IFERROR(SUMIF('Transaction Log'!C5:C106,B46,'Transaction Log'!E5:E106),0) -> 0 | I46: =IFERROR(SUMIF('Transaction Log'!C5:C106,B46,'Transaction Log'!F5:F106),0) -> 0 | J46: =IFERROR(H46-I46,0) -> 0 | K46: =IFERROR(J46/(IFERROR(LOOKUP(2,1/('Transaction Log'!H5:H106<>""),'Transaction Log'!H5:H106),0)),0) -> 0 | L46: =IFERROR(SUM(Positions!Q6:Q105),0) -> 1.1832186e+09 | M46: =IFERROR(K46*L46,0) -> 0 | P46: =IFERROR(O46/J46,0) -> 0 | Q46: =IFERROR(P46*M46,0) -> 0 | R46: =IFERROR(IF(O46>0,O46+Q46,""),"") | S46: =IFERROR(J46-O46,J46) -> 0 | T46: =IFERROR(S46/(IFERROR(LOOKUP(2,1/('Transaction Log'!H5:H106<>""),'Transaction Log'!H5:H106),0)),0) -> 0 | U46: =IFERROR(IF(J46<=0,"No Balance",IF(O46<=0,"No Withdrawal",IF(TODAY()<E46,"LOCKED",IF(O46>J46,"Exceeds Balance","Approved")))),"—") -> No Balance
A47: 42 | E47: =IFERROR(C47+D47,"") -> 0 | F47: =IFERROR(E47-TODAY(),"") -> -46096 | G47: =IFERROR(IF(TODAY()>=E47,"UNLOCKED","LOCKED"),"") -> UNLOCKED | H47: =IFERROR(SUMIF('Transaction Log'!C5:C106,B47,'Transaction Log'!E5:E106),0) -> 0 | I47: =IFERROR(SUMIF('Transaction Log'!C5:C106,B47,'Transaction Log'!F5:F106),0) -> 0 | J47: =IFERROR(H47-I47,0) -> 0 | K47: =IFERROR(J47/(IFERROR(LOOKUP(2,1/('Transaction Log'!H5:H106<>""),'Transaction Log'!H5:H106),0)),0) -> 0 | L47: =IFERROR(SUM(Positions!Q6:Q105),0) -> 1.1832186e+09 | M47: =IFERROR(K47*L47,0) -> 0 | P47: =IFERROR(O47/J47,0) -> 0 | Q47: =IFERROR(P47*M47,0) -> 0 | R47: =IFERROR(IF(O47>0,O47+Q47,""),"") | S47: =IFERROR(J47-O47,J47) -> 0 | T47: =IFERROR(S47/(IFERROR(LOOKUP(2,1/('Transaction Log'!H5:H106<>""),'Transaction Log'!H5:H106),0)),0) -> 0 | U47: =IFERROR(IF(J47<=0,"No Balance",IF(O47<=0,"No Withdrawal",IF(TODAY()<E47,"LOCKED",IF(O47>J47,"Exceeds Balance","Approved")))),"—") -> No Balance
A48: 43 | E48: =IFERROR(C48+D48,"") -> 0 | F48: =IFERROR(E48-TODAY(),"") -> -46096 | G48: =IFERROR(IF(TODAY()>=E48,"UNLOCKED","LOCKED"),"") -> UNLOCKED | H48: =IFERROR(SUMIF('Transaction Log'!C5:C106,B48,'Transaction Log'!E5:E106),0) -> 0 | I48: =IFERROR(SUMIF('Transaction Log'!C5:C106,B48,'Transaction Log'!F5:F106),0) -> 0 | J48: =IFERROR(H48-I48,0) -> 0 | K48: =IFERROR(J48/(IFERROR(LOOKUP(2,1/('Transaction Log'!H5:H106<>""),'Transaction Log'!H5:H106),0)),0) -> 0 | L48: =IFERROR(SUM(Positions!Q6:Q105),0) -> 1.1832186e+09 | M48: =IFERROR(K48*L48,0) -> 0 | P48: =IFERROR(O48/J48,0) -> 0 | Q48: =IFERROR(P48*M48,0) -> 0 | R48: =IFERROR(IF(O48>0,O48+Q48,""),"") | S48: =IFERROR(J48-O48,J48) -> 0 | T48: =IFERROR(S48/(IFERROR(LOOKUP(2,1/('Transaction Log'!H5:H106<>""),'Transaction Log'!H5:H106),0)),0) -> 0 | U48: =IFERROR(IF(J48<=0,"No Balance",IF(O48<=0,"No Withdrawal",IF(TODAY()<E48,"LOCKED",IF(O48>J48,"Exceeds Balance","Approved")))),"—") -> No Balance
A49: 44 | E49: =IFERROR(C49+D49,"") -> 0 | F49: =IFERROR(E49-TODAY(),"") -> -46096 | G49: =IFERROR(IF(TODAY()>=E49,"UNLOCKED","LOCKED"),"") -> UNLOCKED | H49: =IFERROR(SUMIF('Transaction Log'!C5:C106,B49,'Transaction Log'!E5:E106),0) -> 0 | I49: =IFERROR(SUMIF('Transaction Log'!C5:C106,B49,'Transaction Log'!F5:F106),0) -> 0 | J49: =IFERROR(H49-I49,0) -> 0 | K49: =IFERROR(J49/(IFERROR(LOOKUP(2,1/('Transaction Log'!H5:H106<>""),'Transaction Log'!H5:H106),0)),0) -> 0 | L49: =IFERROR(SUM(Positions!Q6:Q105),0) -> 1.1832186e+09 | M49: =IFERROR(K49*L49,0) -> 0 | P49: =IFERROR(O49/J49,0) -> 0 | Q49: =IFERROR(P49*M49,0) -> 0 | R49: =IFERROR(IF(O49>0,O49+Q49,""),"") | S49: =IFERROR(J49-O49,J49) -> 0 | T49: =IFERROR(S49/(IFERROR(LOOKUP(2,1/('Transaction Log'!H5:H106<>""),'Transaction Log'!H5:H106),0)),0) -> 0 | U49: =IFERROR(IF(J49<=0,"No Balance",IF(O49<=0,"No Withdrawal",IF(TODAY()<E49,"LOCKED",IF(O49>J49,"Exceeds Balance","Approved")))),"—") -> No Balance
A50: 45 | E50: =IFERROR(C50+D50,"") -> 0 | F50: =IFERROR(E50-TODAY(),"") -> -46096 | G50: =IFERROR(IF(TODAY()>=E50,"UNLOCKED","LOCKED"),"") -> UNLOCKED | H50: =IFERROR(SUMIF('Transaction Log'!C5:C106,B50,'Transaction Log'!E5:E106),0) -> 0 | I50: =IFERROR(SUMIF('Transaction Log'!C5:C106,B50,'Transaction Log'!F5:F106),0) -> 0 | J50: =IFERROR(H50-I50,0) -> 0 | K50: =IFERROR(J50/(IFERROR(LOOKUP(2,1/('Transaction Log'!H5:H106<>""),'Transaction Log'!H5:H106),0)),0) -> 0 | L50: =IFERROR(SUM(Positions!Q6:Q105),0) -> 1.1832186e+09 | M50: =IFERROR(K50*L50,0) -> 0 | P50: =IFERROR(O50/J50,0) -> 0 | Q50: =IFERROR(P50*M50,0) -> 0 | R50: =IFERROR(IF(O50>0,O50+Q50,""),"") | S50: =IFERROR(J50-O50,J50) -> 0 | T50: =IFERROR(S50/(IFERROR(LOOKUP(2,1/('Transaction Log'!H5:H106<>""),'Transaction Log'!H5:H106),0)),0) -> 0 | U50: =IFERROR(IF(J50<=0,"No Balance",IF(O50<=0,"No Withdrawal",IF(TODAY()<E50,"LOCKED",IF(O50>J50,"Exceeds Balance","Approved")))),"—") -> No Balance
A51: 46 | E51: =IFERROR(C51+D51,"") -> 0 | F51: =IFERROR(E51-TODAY(),"") -> -46096 | G51: =IFERROR(IF(TODAY()>=E51,"UNLOCKED","LOCKED"),"") -> UNLOCKED | H51: =IFERROR(SUMIF('Transaction Log'!C5:C106,B51,'Transaction Log'!E5:E106),0) -> 0 | I51: =IFERROR(SUMIF('Transaction Log'!C5:C106,B51,'Transaction Log'!F5:F106),0) -> 0 | J51: =IFERROR(H51-I51,0) -> 0 | K51: =IFERROR(J51/(IFERROR(LOOKUP(2,1/('Transaction Log'!H5:H106<>""),'Transaction Log'!H5:H106),0)),0) -> 0 | L51: =IFERROR(SUM(Positions!Q6:Q105),0) -> 1.1832186e+09 | M51: =IFERROR(K51*L51,0) -> 0 | P51: =IFERROR(O51/J51,0) -> 0 | Q51: =IFERROR(P51*M51,0) -> 0 | R51: =IFERROR(IF(O51>0,O51+Q51,""),"") | S51: =IFERROR(J51-O51,J51) -> 0 | T51: =IFERROR(S51/(IFERROR(LOOKUP(2,1/('Transaction Log'!H5:H106<>""),'Transaction Log'!H5:H106),0)),0) -> 0 | U51: =IFERROR(IF(J51<=0,"No Balance",IF(O51<=0,"No Withdrawal",IF(TODAY()<E51,"LOCKED",IF(O51>J51,"Exceeds Balance","Approved")))),"—") -> No Balance
A52: 47 | E52: =IFERROR(C52+D52,"") -> 0 | F52: =IFERROR(E52-TODAY(),"") -> -46096 | G52: =IFERROR(IF(TODAY()>=E52,"UNLOCKED","LOCKED"),"") -> UNLOCKED | H52: =IFERROR(SUMIF('Transaction Log'!C5:C106,B52,'Transaction Log'!E5:E106),0) -> 0 | I52: =IFERROR(SUMIF('Transaction Log'!C5:C106,B52,'Transaction Log'!F5:F106),0) -> 0 | J52: =IFERROR(H52-I52,0) -> 0 | K52: =IFERROR(J52/(IFERROR(LOOKUP(2,1/('Transaction Log'!H5:H106<>""),'Transaction Log'!H5:H106),0)),0) -> 0 | L52: =IFERROR(SUM(Positions!Q6:Q105),0) -> 1.1832186e+09 | M52: =IFERROR(K52*L52,0) -> 0 | P52: =IFERROR(O52/J52,0) -> 0 | Q52: =IFERROR(P52*M52,0) -> 0 | R52: =IFERROR(IF(O52>0,O52+Q52,""),"") | S52: =IFERROR(J52-O52,J52) -> 0 | T52: =IFERROR(S52/(IFERROR(LOOKUP(2,1/('Transaction Log'!H5:H106<>""),'Transaction Log'!H5:H106),0)),0) -> 0 | U52: =IFERROR(IF(J52<=0,"No Balance",IF(O52<=0,"No Withdrawal",IF(TODAY()<E52,"LOCKED",IF(O52>J52,"Exceeds Balance","Approved")))),"—") -> No Balance
A53: 48 | E53: =IFERROR(C53+D53,"") -> 0 | F53: =IFERROR(E53-TODAY(),"") -> -46096 | G53: =IFERROR(IF(TODAY()>=E53,"UNLOCKED","LOCKED"),"") -> UNLOCKED | H53: =IFERROR(SUMIF('Transaction Log'!C5:C106,B53,'Transaction Log'!E5:E106),0) -> 0 | I53: =IFERROR(SUMIF('Transaction Log'!C5:C106,B53,'Transaction Log'!F5:F106),0) -> 0 | J53: =IFERROR(H53-I53,0) -> 0 | K53: =IFERROR(J53/(IFERROR(LOOKUP(2,1/('Transaction Log'!H5:H106<>""),'Transaction Log'!H5:H106),0)),0) -> 0 | L53: =IFERROR(SUM(Positions!Q6:Q105),0) -> 1.1832186e+09 | M53: =IFERROR(K53*L53,0) -> 0 | P53: =IFERROR(O53/J53,0) -> 0 | Q53: =IFERROR(P53*M53,0) -> 0 | R53: =IFERROR(IF(O53>0,O53+Q53,""),"") | S53: =IFERROR(J53-O53,J53) -> 0 | T53: =IFERROR(S53/(IFERROR(LOOKUP(2,1/('Transaction Log'!H5:H106<>""),'Transaction Log'!H5:H106),0)),0) -> 0 | U53: =IFERROR(IF(J53<=0,"No Balance",IF(O53<=0,"No Withdrawal",IF(TODAY()<E53,"LOCKED",IF(O53>J53,"Exceeds Balance","Approved")))),"—") -> No Balance
A54: 49 | E54: =IFERROR(C54+D54,"") -> 0 | F54: =IFERROR(E54-TODAY(),"") -> -46096 | G54: =IFERROR(IF(TODAY()>=E54,"UNLOCKED","LOCKED"),"") -> UNLOCKED | H54: =IFERROR(SUMIF('Transaction Log'!C5:C106,B54,'Transaction Log'!E5:E106),0) -> 0 | I54: =IFERROR(SUMIF('Transaction Log'!C5:C106,B54,'Transaction Log'!F5:F106),0) -> 0 | J54: =IFERROR(H54-I54,0) -> 0 | K54: =IFERROR(J54/(IFERROR(LOOKUP(2,1/('Transaction Log'!H5:H106<>""),'Transaction Log'!H5:H106),0)),0) -> 0 | L54: =IFERROR(SUM(Positions!Q6:Q105),0) -> 1.1832186e+09 | M54: =IFERROR(K54*L54,0) -> 0 | P54: =IFERROR(O54/J54,0) -> 0 | Q54: =IFERROR(P54*M54,0) -> 0 | R54: =IFERROR(IF(O54>0,O54+Q54,""),"") | S54: =IFERROR(J54-O54,J54) -> 0 | T54: =IFERROR(S54/(IFERROR(LOOKUP(2,1/('Transaction Log'!H5:H106<>""),'Transaction Log'!H5:H106),0)),0) -> 0 | U54: =IFERROR(IF(J54<=0,"No Balance",IF(O54<=0,"No Withdrawal",IF(TODAY()<E54,"LOCKED",IF(O54>J54,"Exceeds Balance","Approved")))),"—") -> No Balance
A55: 50 | E55: =IFERROR(C55+D55,"") -> 0 | F55: =IFERROR(E55-TODAY(),"") -> -46096 | G55: =IFERROR(IF(TODAY()>=E55,"UNLOCKED","LOCKED"),"") -> UNLOCKED | H55: =IFERROR(SUMIF('Transaction Log'!C5:C106,B55,'Transaction Log'!E5:E106),0) -> 0 | I55: =IFERROR(SUMIF('Transaction Log'!C5:C106,B55,'Transaction Log'!F5:F106),0) -> 0 | J55: =IFERROR(H55-I55,0) -> 0 | K55: =IFERROR(J55/(IFERROR(LOOKUP(2,1/('Transaction Log'!H5:H106<>""),'Transaction Log'!H5:H106),0)),0) -> 0 | L55: =IFERROR(SUM(Positions!Q6:Q105),0) -> 1.1832186e+09 | M55: =IFERROR(K55*L55,0) -> 0 | P55: =IFERROR(O55/J55,0) -> 0 | Q55: =IFERROR(P55*M55,0) -> 0 | R55: =IFERROR(IF(O55>0,O55+Q55,""),"") | S55: =IFERROR(J55-O55,J55) -> 0 | T55: =IFERROR(S55/(IFERROR(LOOKUP(2,1/('Transaction Log'!H5:H106<>""),'Transaction Log'!H5:H106),0)),0) -> 0 | U55: =IFERROR(IF(J55<=0,"No Balance",IF(O55<=0,"No Withdrawal",IF(TODAY()<E55,"LOCKED",IF(O55>J55,"Exceeds Balance","Approved")))),"—") -> No Balance

Sheet Fund Measures
A1: FUND MEASURES // PERFORMANCE ANALYTICS | D1: ="DATE: "&TEXT(TODAY(),"DD.MM.YYYY") -> DATE: DD.03.YYYY
A2: All metrics live from Transaction Log + Positions.
B4: RETURNS
B5: Total Capital Deposited ($) | C5: =SUM('Transaction Log'!E5:E106) -> 2050000000 | D5: Sum of all player deposits
B6: Current Fund Balance ($) | C6: =IFERROR(LOOKUP(2,1/('Transaction Log'!H5:H106<>""),'Transaction Log'!H5:H106),0) -> 2050000000 | D6: Latest balance from Transaction Log
B7: Unrealised P&L ($) | C7: =SUMIF(Positions!B6:B105,"Open",Positions!Q6:Q105) -> 43080000 | D7: Open positions at current prices
B8: Realised P&L ($) | C8: =SUMIF(Positions!B6:B105,"Closed",Positions!Q6:Q105) -> 1.1401386e+09 | D8: Closed positions locked P&L
B9: Total P&L ($) | C9: =SUM(Positions!Q6:Q105) -> 1.1832186e+09 | D9: Unrealised + Realised combined
B10: Fund NAV ($) | C10: =IFERROR(LOOKUP(2,1/('Transaction Log'!H5:H106<>""),'Transaction Log'!H5:H106),0)+SUM(Positions!Q6:Q105) -> 3.2332186e+09 | D10: Cash balance + total P&L
B11: Total Return (%) | C11: =IFERROR(SUM(Positions!Q6:Q105)/SUM('Transaction Log'!E5:E106),0) -> 0.57717979 | D11: Total P&L / Total Capital Deposited
B12: RISK & DRAWDOWN
B13: Peak Fund Balance ($) | C13: =IFERROR(MAX('Transaction Log'!H5:H106),0) -> 2050000000 | D13: Highest balance in Transaction Log
B14: Current Drawdown ($) | C14: =IFERROR(MAX('Transaction Log'!H5:H106)-LOOKUP(2,1/('Transaction Log'!H5:H106<>""),'Transaction Log'!H5:H106),0) -> 0 | D14: Peak minus current balance
B15: Current Drawdown (%) | C15: =IFERROR(IF(MAX('Transaction Log'!H5:H106)=0,"—",(MAX('Transaction Log'!H5:H106)-LOOKUP(2,1/('Transaction Log'!H5:H106<>""),'Transaction Log'!H5:H106))/MAX('Transaction Log'!H5:H106)),"—") -> 0 | D15: How far below peak (%)
B16: Max Potential Loss ($) | C16: =SUMIF(Positions!B6:B105,"Open",Positions!AC6:AC105) -> 2.2532e+08 | D16: Sum of SL distances for open positions
B17: Total Notional Exposure ($) | C17: =SUMIF(Positions!B6:B105,"Open",Positions!K6:K105) -> 3905320000 | D17: Total leveraged exposure of open positions
B18: Margin Deployed ($) | C18: =SUMIF(Positions!B6:B105,"Open",Positions!L6:L105) -> 195266000 | D18: Capital committed as margin on open positions
B19: Active Liquidations | C19: =COUNTIF(Positions!N6:N105,"LIQUIDATION") -> 0 | D19: Open positions at/below maintenance margin
B20: TRADE STATISTICS
B21: Total Trades (Closed) | C21: =COUNTIF(Positions!B6:B105,"Closed") -> 23 | D21: Completed trades
B22: Winning Trades | C22: =COUNTIFS(Positions!B6:B105,"Closed",Positions!Q6:Q105,">"&0) -> 20 | D22: Closed trades with positive P&L
B23: Losing Trades | C23: =COUNTIFS(Positions!B6:B105,"Closed",Positions!Q6:Q105,"<"&0) -> 3 | D23: Closed trades with negative P&L
B24: Win Rate (%) | C24: =IFERROR(COUNTIFS(Positions!B6:B105,"Closed",Positions!Q6:Q105,">"&0)/COUNTIF(Positions!B6:B105,"Closed"),0) -> 0.86956522 | D24: % of closed trades profitable
B25: Average P&L per Trade ($) | C25: =IFERROR(SUM(Positions!Q6:Q105)/COUNTIF(Positions!B6:B105,"Closed"),0) -> 51444285 | D25: Mean P&L across all trades
B26: Average Winning Trade ($) | C26: =IFERROR(SUMPRODUCT((Positions!B6:B105="Closed")*(Positions!Q6:Q105>0)*Positions!Q6:Q105)/COUNTIFS(Positions!B6:B105,"Closed",Positions!Q6:Q105,">"&0),0) -> 66169178 | D26: Mean P&L of winning closed trades
B27: Average Losing Trade ($) | C27: =IFERROR(SUMPRODUCT((Positions!B6:B105="Closed")*(Positions!Q6:Q105<0)*Positions!Q6:Q105)/COUNTIFS(Positions!B6:B105,"Closed",Positions!Q6:Q105,"<"&0),0) -> -61081667 | D27: Mean P&L of losing closed trades
B28: Best Trade ($) | C28: =IFERROR(_xlfn.SINGLE(_xlfn.MAXIFS(Positions!Q6:Q105, Positions!B6:B105, "Closed")), 0) -> 4.08384e+08 | D28: Highest P&L single closed trade
B29: Worst Trade ($) | C29: =IFERROR(_xlfn.SINGLE(_xlfn.MINIFS(Positions!Q6:Q105, Positions!B6:B105, "Closed", Positions!Q6:Q105, "<0")), 0) -> -1.21e+08 | D29: Largest loss single closed trade
B30: Profit Factor | C30: =IFERROR(SUMPRODUCT((Positions!B6:B105="Closed")*(Positions!Q6:Q105>0)*Positions!Q6:Q105)/ABS(SUMPRODUCT((Positions!B6:B105="Closed")*(Positions!Q6:Q105<0)*Positions!Q6:Q105)),0) -> 7.2219354 | D30: Gross wins / Gross losses. >1 = profitable
B31: RISK-ADJUSTED
B32: Avg Hold Period — Closed (days) | C32: =IFERROR(AVERAGEIF(Positions!B6:B105,"Closed",Positions!U6:U105),0) -> 1.0869565 | D32: Avg days held for closed positions
B33: Sharpe Ratio (trade-based) | C33: =IFERROR(AVERAGE(Positions!R6:R105)/STDEV(Positions!R6:R105),0) -> 0.62424545 | D33: Avg P&L% / StdDev P&L%
B34: Expectancy ($ per trade) | C34: =IFERROR((COUNTIFS(Positions!B6:B105,"Closed",Positions!Q6:Q105,">"&0)/COUNTIF(Positions!B6:B105,"Closed"))*IFERROR(SUMPRODUCT((Positions!B6:B105="Closed")*(Positions!Q6:Q105>0)*Positions!Q6:Q105)/COUNTIFS(Positions!B6:B105,"Closed",Positions!Q6:Q105,">"&0),0)+(COUNTIFS(Positions!B6:B105,"Closed",Positions!Q6:Q105,"<"&0)/COUNTIF(Positions!B6:B105,"Closed"))*IFERROR(SUMPRODUCT((Positions!B6:B105="Closed")*(Positions!Q6:Q105<0)*Positions!Q6:Q105)/COUNTIFS(Positions!B6:B105,"Closed",Positions!Q6:Q105,"<"&0),0),0) -> 49571242 | D34: WinRate x AvgWin + LossRate x AvgLoss
B35: SL / TP STATUS
B36: Stop Loss Hits (Closed) | C36: =COUNTIF(Positions!AF6:AF105,"STOP LOSS HIT") -> 4 | D36: Live count from Positions sheet
B37: Take Profit Hits (Closed) | C37: =COUNTIF(Positions!AF6:AF105,"TAKE PROFIT HIT") -> 16 | D37: Live count from Positions sheet
B38: Positions Still Active | C38: =COUNTIF(Positions!AF6:AF105,"Active") -> 2 | D38: Live count from Positions sheet

Sheet Fund Summary
A1: FUND SUMMARY // LIVE DASHBOARD
A2: All values auto-calculated from Transaction Log and Positions.
B4: METRIC | C4: VALUE | D4: NOTES
B5: Total Deposits | C5: =SUM('Transaction Log'!E5:E106) -> 2050000000 | D5: Sum of all inflows
B6: Total Withdrawals | C6: =SUM('Transaction Log'!F5:F106) -> 0 | D6: Sum of all outflows
B7: Net Capital Flow | C7: =SUM('Transaction Log'!G5:G106) -> 2050000000 | D7: Deposits − Withdrawals
B8: Current Fund Balance | C8: =IFERROR(LOOKUP(2,1/('Transaction Log'!H5:H106<>""),'Transaction Log'!H5:H106),0) -> 2050000000 | D8: Latest running balance
B9: # of Transactions | C9: =COUNTA('Transaction Log'!C5:C106) -> 2 | D9: Filled player rows
B10: Last Transaction Date | C10: =IFERROR(LOOKUP(2,1/('Transaction Log'!B5:B106<>""),'Transaction Log'!B5:B106),"—") -> 46093 | D10: Most recent entry
B12: Open Positions | C12: =COUNTIF(Positions!B6:B105,"Open") -> 2
B13: Closed Positions | C13: =COUNTIF(Positions!B6:B105,"Closed") -> 23
B14: Total Notional Exp ($) | C14: =SUMIF(Positions!B6:B105,"Open",Positions!K6:K105) -> 3905320000
B15: Margin Deployed ($) | C15: =SUMIF(Positions!B6:B105,"Open",Positions!L6:L105) -> 195266000
B16: Unrealised P&L ($) | C16: =SUMIF(Positions!B6:B105,"Open",Positions!Q6:Q105) -> 43080000
B17: Realised P&L ($) | C17: =SUMIF(Positions!B6:B105,"Closed",Positions!Q6:Q105) -> 1.1401386e+09
B18: Total P&L ($) | C18: =SUM(Positions!Q6:Q105) -> 1.1832186e+09
B19: Active Liquidations | C19: =COUNTIF(Positions!N6:N105,"LIQUIDATION") -> 0
B20: Total Withdrawal Payouts ($) | C20: =IFERROR(SUM('Investor Withdrawals'!R6:R55),0) -> 78858989
B21: Fund NAV ($) | C21: =IFERROR(LOOKUP(2,1/('Transaction Log'!H5:H106<>""),'Transaction Log'!H5:H106),0)+SUM(Positions!Q6:Q105) -> 3.2332186e+09 | D21: Cash + Total P&L
B22: PLAYER SUMMARY
B23: Player Name | C23: Total Deposited | D23: Total Withdrawn
B24: Kimmo | C24: =SUMPRODUCT(('Transaction Log'!C5:C106=B24)*('Transaction Log'!E5:E106)) -> 2000000000 | D24: =SUMPRODUCT(('Transaction Log'!C5:C106=B24)*('Transaction Log'!F5:F106)) -> 0
B25: Andre | C25: =SUMPRODUCT(('Transaction Log'!C5:C106=B25)*('Transaction Log'!E5:E106)) -> 50000000 | D25: =SUMPRODUCT(('Transaction Log'!C5:C106=B25)*('Transaction Log'!F5:F106)) -> 0

Sheet Multi
A1: STAKE FACTOR
A2: Cash flows in and out. Fund Balance auto-updates every row.
A4: Level | B4: Stake Multiplier | C4: Min Bet (10× Scale) | D4: Notes
A5: =IFERROR(ROW()-4,"") -> 1 | B5: 1× | C5: 5
A6: =IFERROR(ROW()-4,"") -> 2 | B6: 10× | C6: 50
A7: =IFERROR(ROW()-4,"") -> 3 | B7: 100× | C7: 500
A8: =IFERROR(ROW()-4,"") -> 4 | B8: 1,000× | C8: 5000
A9: =IFERROR(ROW()-4,"") -> 5 | B9: 10,000× | C9: 50000
A10: =IFERROR(ROW()-4,"") -> 6 | B10: 100,000× | C10: 500000
A11: =IFERROR(ROW()-4,"") -> 7 | B11: 1,000,000× | C11: 5000000
A12: =IFERROR(ROW()-4,"") -> 8 | B12: 10,000,000× | C12: 50000000

Sheet Instructions
B1: HOW TO USE THIS HEDGE FUND TRACKER
B3: 1. LOGGING A TRANSACTION
B4: → Go to the 'Transaction Log' sheet.
B5: → Find the next empty row (blue-text cells).
B6: → Enter: Date · Player Name · Type (Deposit or Withdrawal).
B7: → Enter the amount in 'Deposit (+)' OR 'Withdrawal (−)' — never both.
B8: → Optionally add a note in the 'Note / Reference' column.
B9: → The Net Flow and Fund Balance columns update automatically.
B10: 2. FUND BALANCE
B11: → Column H ('Fund Balance After') shows the exact fund balance after every transaction.
B12: → The Fund Summary dashboard mirrors these live figures.
B13: 3. COLOUR CODING
... B25: → Named table references (Excel) replaced with explicit ranges throughout.
